[{"id":"_7tjvnyw8cf3","number":440,"name":"ALAMO F. RAMON","tel":"2915778367","os":"IOMA","study":"CADERAS F","cash":"800","card":0,"studyType":"radiografia","doctor":"Carla","date":"Mon Dec 12 2022 18:16:18 GMT-0300 (hora estándar de Argentina)","color":"carmen"},{"id":"_k4rhehxanbn","number":439,"name":"PLAZA FABIANA","tel":"2914496843","os":"SWISS","study":"LUMBAR F, P, AMBAS OBL Y FERGUSON","cash":0,"card":0,"studyType":"radiografia","doctor":"Carla","date":"Mon Dec 12 2022 18:13:36 GMT-0300 (hora estándar de Argentina)","color":"alicia"},{"id":"_qixsy24v48","number":438,"name":"DE RENZIS MAXIMO","tel":"1151576368","os":"OSDE","study":"DENTAL","cash":0,"card":0,"studyType":"radiografia","doctor":"Carla","date":"Mon Dec 12 2022 18:09:12 GMT-0300 (hora estándar de Argentina)","color":"carmen"},{"id":"_l3r692tapq","number":437,"name":"GARCIA RODRIGO","tel":"2914131525","os":"FEDERADA","study":"MNP","cash":"500","card":0,"studyType":"radiografia","doctor":"Carla","date":"Mon Dec 12 2022 18:07:21 GMT-0300 (hora estándar de Argentina)","color":"alicia"},{"id":"_uxupitvi7x","number":436,"name":"RIVAROLA CARLOS","tel":"154623702","os":"OSPBB","study":"CODO F Y P","cash":"500","card":0,"studyType":"radiografia","doctor":"Carla","date":"Mon Dec 12 2022 18:04:01 GMT-0300 (hora estándar de Argentina)","color":"carmen"},{"id":"_pcriav8ofz","number":435,"name":"GOMEZ GERALDINA","tel":"2915074436","os":"IOMA","study":"TORAX F","cash":"800","card":0,"studyType":"radiografia","doctor":"Carla","date":"Mon Dec 12 2022 18:00:00 GMT-0300 (hora estándar de Argentina)","color":"carmen"},{"id":"_q69apxdep3q","number":434,"name":"CABRE MATHILDA","tel":"5057510","os":"OSDE","study":"CADERAS F Y LOWERSTEIN","cash":0,"card":0,"studyType":"radiografia","doctor":"Carla","date":"Mon Dec 12 2022 17:58:41 GMT-0300 (hora estándar de Argentina)","color":"alicia"},{"id":"_3brptfj9ghz","number":433,"name":" HERNANDEZ AILIN","tel":"154254874","os":"FEDERADA","study":"DENTAL","cash":"500","card":0,"studyType":"radiografia","doctor":"Carla","date":"Mon Dec 12 2022 17:53:11 GMT-0300 (hora estándar de Argentina)","color":"carmen"},{"id":"_6s5kiv9fym6","number":432,"name":"QUIÑENAO FEDERICO","tel":"2915260293","os":"PART","study":"DENTAL","cash":"2300","card":0,"studyType":"radiografia","doctor":"Carla","date":"Mon Dec 12 2022 17:45:59 GMT-0300 (hora estándar de Argentina)","color":"carmen"},{"id":"_tq10turuu79","number":431,"name":"VASQUEZ ALEXIS","tel":"156418021","os":"CDONSTRUIR","study":"DENTAL","cash":0,"card":"500","studyType":"radiografia","doctor":"Carla","date":"Mon Dec 12 2022 17:39:36 GMT-0300 (hora estándar de Argentina)","color":"carmen"},{"id":"_endsy0mu8bt","number":430,"name":"PENDAS ISABELLA","tel":"154232915","os":"OSPEDYC","study":"DENTAL","cash":0,"card":"500","studyType":"radiografia","doctor":"Carla","date":"Mon Dec 12 2022 17:35:07 GMT-0300 (hora estándar de Argentina)","color":"carmen"},{"id":"_re574fxlfta","number":429,"name":"RAMELLO CARINA","tel":"2916469137","os":"PART","study":"DENTAL","cash":"2300","card":0,"studyType":"radiografia","doctor":"Carla","date":"Mon Dec 12 2022 17:32:31 GMT-0300 (hora estándar de Argentina)","color":"carmen"},{"id":"_9fmhvytjv9i","number":428,"name":"MARINANGELI MARIELA","tel":"2915738869","os":"IOMA","study":"LUMBAR F, P Y CADERAS F Y P","cash":"1500","card":0,"studyType":"radiografia","doctor":"Carla","date":"Mon Dec 12 2022 17:30:54 GMT-0300 (hora estándar de Argentina)","color":"alicia"},{"id":"_7u7zgesnpn5","number":427,"name":"MEDINA COSTA THIAGO","tel":"2915718986","os":"OSDE","study":"TORAX F Y P","cash":0,"card":0,"studyType":"radiografia","doctor":"Carla","date":"Mon Dec 12 2022 17:27:42 GMT-0300 (hora estándar de Argentina)","color":"carmen"},{"id":"_furvy04cuhv","number":426,"name":"MOREIRA ROCIO","tel":"2915763649","os":"PART","study":"TOMO DE 14 15","cash":"3900","card":0,"studyType":"radiografia","doctor":"Carla","date":"Mon Dec 12 2022 17:20:29 GMT-0300 (hora estándar de Argentina)","color1":"red","color":"carmen"},{"id":"_efb5v9bm49k","number":425,"name":"BOQUEZ GENNARO","tel":"154474477","os":"PREVENCION","study":"DENTAL Y TELE","cash":"500","card":0,"studyType":"radiografia","doctor":"Carla","date":"Mon Dec 12 2022 17:07:44 GMT-0300 (hora estándar de Argentina)","color":"carmen"},{"id":"_gy48c1qutyn","number":424,"name":"ARROYO  ELIZABETH","tel":"2914464483","os":"UNS","study":"DENTAL","cash":0,"card":0,"studyType":"radiografia","doctor":"Carla","date":"Mon Dec 12 2022 17:04:23 GMT-0300 (hora estándar de Argentina)","color":"carmen"},{"id":"_9e750rrbypp","number":423,"name":"DARINO NOEMI","tel":"154188019","os":"JERARQUICO S","study":"RODILLAS F Y P","cash":"500","card":0,"studyType":"radiografia","doctor":"Carla","date":"Mon Dec 12 2022 17:02:01 GMT-0300 (hora estándar de Argentina)","color":"carmen"},{"id":"_9hwh493rxxi","number":422,"name":"MONTERRUBIO ANA","tel":"2914180177","os":"IOMA","study":"TORAX F Y P","cash":"800","card":0,"studyType":"radiografia","doctor":"Carla","date":"Mon Dec 12 2022 16:57:24 GMT-0300 (hora estándar de Argentina)","color":"carmen"},{"id":"_uo8xtq2adk","number":421,"name":"MERCADO MARTIN","tel":"2262508742","os":"SWISS","study":"DENTAL","cash":0,"card":0,"studyType":"radiografia","doctor":"Carla","date":"Mon Dec 12 2022 16:51:29 GMT-0300 (hora estándar de Argentina)","color":"carmen"},{"id":"_ts3u5jx4voa","number":420,"name":"BANEGA LUCIANO","tel":"1111111111","os":"DOSEM","study":"TORAX F Y P","cash":"500","card":0,"studyType":"radiografia","doctor":"Carla","date":"Mon Dec 12 2022 16:45:50 GMT-0300 (hora estándar de Argentina)","color":"carmen"},{"id":"_fa9zxp7wut","number":419,"name":"FUENTEALBA DANA","tel":"2914165475","os":"OSPRERA","study":"BRAZO F Y P","cash":"1700","card":0,"studyType":"radiografia","doctor":"Carla","date":"Mon Dec 12 2022 16:39:00 GMT-0300 (hora estándar de Argentina)","color":"carmen"},{"id":"_l33b6373hvc","number":418,"name":"ROSSI FIORELLA","tel":"154484785","os":"UNS","study":"DENTAL","cash":0,"card":0,"studyType":"radiografia","doctor":"Carla","date":"Mon Dec 12 2022 16:33:16 GMT-0300 (hora estándar de Argentina)","color":"carmen"},{"id":"_y8cvd1kj3sj","number":417,"name":"AZZINI JIMENA","tel":"2914078265","os":"OSDE","study":"ESPINO F Y P","cash":0,"card":0,"studyType":"radiografia","doctor":"Carla","date":"Mon Dec 12 2022 16:32:15 GMT-0300 (hora estándar de Argentina)","color":"carmen"},{"id":"_n3aqxh43ojk","number":416,"name":"MASSON MILENA","tel":"2916429168","os":"UNS","study":"DENTAL","cash":0,"card":0,"studyType":"radiografia","doctor":"Carla","date":"Mon Dec 12 2022 16:21:29 GMT-0300 (hora estándar de Argentina)","color":"carmen"},{"id":"_932jevuw7j9","number":415,"name":"MASSARI EDGARDO","tel":"2914278543","os":"PART","study":"DENTAL","cash":0,"card":"2300","studyType":"radiografia","doctor":"Carla","date":"Mon Dec 12 2022 16:18:07 GMT-0300 (hora estándar de Argentina)","color":"carmen"},{"id":"_d2tmqkni8wr","number":414,"name":"RODRIGUEZ FACUNDO","tel":"155102715","os":"PART","study":"DENTAL","cash":"2300","card":0,"studyType":"radiografia","doctor":"Carla","date":"Mon Dec 12 2022 16:15:24 GMT-0300 (hora estándar de Argentina)","color":"carmen"},{"id":"_jp0iam28wh","number":413,"name":"GOY MARCELA","tel":"2914278734","os":"OSMATA","study":"AMBAS CADERAS Y RIDILLAS F Y P","cash":"500","card":0,"studyType":"radiografia","doctor":"Carla","date":"Mon Dec 12 2022 16:02:13 GMT-0300 (hora estándar de Argentina)","color":"carmen"},{"id":"_3p5p8bbt5se","number":412,"name":"STROJNY GERONIMO","tel":"154182478","os":"PART","study":"DENTAL","cash":"2300","card":0,"studyType":"radiografia","doctor":"Carla","date":"Mon Dec 12 2022 15:43:23 GMT-0300 (hora estándar de Argentina)","color":"carmen"},{"id":"_thp0k0im1ck","number":411,"name":"STINZIANO JUANA","tel":"2914524956","os":"PART","study":"DENTAL Y ATM","cash":"4600","card":0,"studyType":"radiografia","doctor":"Carla","date":"Mon Dec 12 2022 15:41:39 GMT-0300 (hora estándar de Argentina)","color":"carmen"},{"id":"_vssh7bbn9bg","number":410,"name":"HECHT ADRIANA","tel":"2914412868","os":"IOMA","study":"TOBILLO F Y P","cash":"800","card":0,"studyType":"radiografia","doctor":"Carla","date":"Mon Dec 12 2022 15:37:43 GMT-0300 (hora estándar de Argentina)","color":"alicia"},{"id":"_kwbcp451nfa","number":409,"name":"GERDEZ MELINA","tel":"2914732847","os":"PART","study":"DENTAL","cash":"2300","card":0,"studyType":"radiografia","doctor":"Carla","date":"Mon Dec 12 2022 15:35:22 GMT-0300 (hora estándar de Argentina)","color":"carmen"},{"id":"_8wgkjizhqip","number":408,"name":"CID FACUNDO","tel":"2915016129","os":"CONSTRUIR SALUD","study":"DENTAL","cash":"500","card":0,"studyType":"radiografia","doctor":"Carla","date":"Mon Dec 12 2022 15:33:46 GMT-0300 (hora estándar de Argentina)","color":"carmen"},{"id":"_x6s083duces","number":407,"name":"LAURIA NORMA","tel":"4528519","os":"IOMA","study":"RODILLAS F Y P","cash":0,"card":0,"studyType":"radiografia","doctor":"Carla","date":"Mon Dec 12 2022 15:13:14 GMT-0300 (hora estándar de Argentina)","color":"carmen"},{"id":"_mo5xp17lmrp","number":406,"name":"RIEU CLAUDIO","tel":"2914224393","os":"ESCRIBANOS","study":"DENTAL","cash":0,"card":0,"studyType":"radiografia","doctor":"Carla","date":"Mon Dec 12 2022 15:11:03 GMT-0300 (hora estándar de Argentina)","color":"dami"},{"id":"_i7euczmk08","number":405,"name":"ANCHUVIDART MICAELA","tel":"156414271","os":"IOMA","study":"TELE P","cash":0,"card":"2300","studyType":"radiografia","doctor":"Carla","date":"Mon Dec 12 2022 15:05:32 GMT-0300 (hora estándar de Argentina)","color":"dami"},{"id":"_gbe1n8ywsw","number":404,"name":"PIRES EDGARDO","tel":"2915040451","os":"PART","study":"DENTAL","cash":0,"card":"2300","studyType":"radiografia","doctor":"Carla","date":"Mon Dec 12 2022 14:37:23 GMT-0300 (hora estándar de Argentina)","color":"carmen"},{"id":"_3tfyaf442ow","number":403,"name":"MENENDEZ CAMILA","tel":"2914494585","os":"IOMA","study":"DENTAL","cash":"800","card":0,"studyType":"radiografia","doctor":"Carla","date":"Mon Dec 12 2022 14:18:35 GMT-0300 (hora estándar de Argentina)","color":"carmen"},{"id":"_ga2row1ldi","number":402,"name":"BRITOS JORGE","tel":"2932456495","os":"MEDIFE","study":"DENTA","cash":0,"card":0,"studyType":"radiografia","doctor":"Carla","date":"Mon Dec 12 2022 14:10:43 GMT-0300 (hora estándar de Argentina)","color":"carmen"},{"id":"_4evrsvjfa0c","number":401,"name":"PINTOS GONZALO","tel":"2914727496","os":"SANCO","study":"DENTAL","cash":"500","card":0,"studyType":"radiografia","doctor":"Carla","date":"Mon Dec 12 2022 14:08:43 GMT-0300 (hora estándar de Argentina)","color":"carmen"},{"id":"_941s5stevo","number":400,"name":"NAVARRO FEDERICO","tel":"2926520920","os":"SANCOR","study":"DENTAL","cash":"500","card":0,"studyType":"radiografia","doctor":"Carla","date":"Mon Dec 12 2022 14:07:15 GMT-0300 (hora estándar de Argentina)","color":"carmen"},{"id":"_jxza4xymr2","number":399,"name":"GONZALEZ CECILIA","tel":"2915714346","os":"PREVENCION","study":"DENTAL","cash":0,"card":0,"studyType":"radiografia","doctor":"Carla","date":"Mon Dec 12 2022 14:03:47 GMT-0300 (hora estándar de Argentina)","color":"carmen"},{"id":"_kkx1298682b","number":398,"name":"CONTRERA RAUL","tel":"3814575572","os":"MEDIFE","study":"DENTAL","cash":0,"card":0,"studyType":"radiografia","doctor":"Carla","date":"Mon Dec 12 2022 14:00:34 GMT-0300 (hora estándar de Argentina)","color":"carmen"},{"id":"_3j0esqfqscq","number":397,"name":"LOPEZ ALICIA","tel":"2914273131","os":"IOMA","study":"DENTAL","cash":"800","card":0,"studyType":"radiografia","doctor":"Carla","date":"Mon Dec 12 2022 13:52:16 GMT-0300 (hora estándar de Argentina)","color":"dami"},{"id":"_uupilbokkha","number":396,"name":"FERRETTI MARIA","tel":"4516464","os":"OSSEG","study":"TORAX F","cash":"450","card":0,"studyType":"radiografia","doctor":"Carla","date":"Mon Dec 12 2022 13:45:44 GMT-0300 (hora estándar de Argentina)","color":"carmen"},{"id":"_1k7jkp2sy5i","number":395,"name":"DUMRAUF GONZALO","tel":"2915342132","os":"PART","study":"DENTAL","cash":"2300","card":0,"studyType":"radiografia","doctor":"Carla","date":"Mon Dec 12 2022 13:43:46 GMT-0300 (hora estándar de Argentina)","color":"dami"},{"id":"_4ece6jpwe63","number":394,"name":"CORREA FALCON RAMON","tel":"2914048181","os":"FEDERADA","study":"CLAVICULA","cash":0,"card":0,"studyType":"radiografia","doctor":"Carla","date":"Mon Dec 12 2022 13:36:52 GMT-0300 (hora estándar de Argentina)","color":"sole"},{"id":"_o43tqg2tbmg","number":393,"name":"ROSSELLO ANA","tel":"154369370","os":"MEDIFE","study":"TORAX F Y P","cash":0,"card":0,"studyType":"radiografia","doctor":"Carla","date":"Mon Dec 12 2022 13:35:04 GMT-0300 (hora estándar de Argentina)","color":"sole"},{"id":"_jq2dennp08t","number":392,"name":"VALENTIN NORBERTO","tel":"2915071351","os":"PATRONES CABOTAJE","study":"DENTAL","cash":"500","card":0,"studyType":"radiografia","doctor":"Carla","date":"Mon Dec 12 2022 13:31:18 GMT-0300 (hora estándar de Argentina)","color":"dami"},{"id":"_0tv7nq1boe9m","number":391,"name":"BECERRA THOMAS","tel":"2914190758","os":"OSDE","study":"MNP","cash":0,"card":0,"studyType":"radiografia","doctor":"Carla","date":"Mon Dec 12 2022 13:29:27 GMT-0300 (hora estándar de Argentina)","color":"sole"},{"id":"_xnaub5743gc","number":390,"name":"GARCIA LOPEZ BENJAMIN","tel":"155773171","os":"PART","study":"CADERAS F Y P","cash":"3500","card":0,"studyType":"radiografia","doctor":"Carla","date":"Mon Dec 12 2022 13:21:29 GMT-0300 (hora estándar de Argentina)","color":"sole"},{"id":"_cua476bk59q","number":389,"name":"SAAVEDRA KARINA","tel":"2914255066","os":"PART","study":"DENTAL","cash":"2300","card":0,"studyType":"radiografia","doctor":"Carla","date":"Mon Dec 12 2022 13:16:25 GMT-0300 (hora estándar de Argentina)","color":"dami"},{"id":"_m8vuf21qwmj","number":388,"name":"KULLEFF LILIANA","tel":"4511095","os":"IOMA","study":"LUMBAR FYP","cash":0,"card":0,"studyType":"radiografia","doctor":"Carla","date":"Mon Dec 12 2022 13:14:54 GMT-0300 (hora estándar de Argentina)","color":"sole"},{"id":"_m3n09lvro4i","number":387,"name":"TARC MARIELA","tel":"2914193079","os":"UNS","study":"TORAX F","cash":"500","card":0,"studyType":"radiografia","doctor":"Carla","date":"Mon Dec 12 2022 12:54:12 GMT-0300 (hora estándar de Argentina)","color":"sole"},{"id":"_vxjy7ds1pz","number":386,"name":"MAITERRENA GLADYS","tel":"2914231490","os":"BCO","study":"TORAX FYP","cash":"3500","card":0,"studyType":"radiografia","doctor":"Carla","date":"Mon Dec 12 2022 12:36:30 GMT-0300 (hora estándar de Argentina)","color":"sole"},{"id":"_j8o5gq1n3rk","number":385,"name":"CORONEL SUSANA","tel":"2914618274","os":"IOMA","study":"HOMBROS FYP","cash":"1200","card":0,"studyType":"radiografia","doctor":"Carla","date":"Mon Dec 12 2022 12:29:38 GMT-0300 (hora estándar de Argentina)","color":"sole"},{"id":"_3xaamk9xe95","number":384,"name":"MOSMANN LEANDRO","tel":"2914057952","os":"PART","study":"DENTAL","cash":"2300","card":0,"studyType":"radiografia","doctor":"Carla","date":"Mon Dec 12 2022 12:21:00 GMT-0300 (hora estándar de Argentina)","color":"dami"},{"id":"_aqo88sliuz6","number":383,"name":"RIVARDA INDIA","tel":"2916480894","os":"VISITAR","study":"CADERAS","cash":"500","card":0,"studyType":"radiografia","doctor":"Carla","date":"Mon Dec 12 2022 12:17:56 GMT-0300 (hora estándar de Argentina)","color":"sole"},{"id":"_wysxqmgjjrb","number":382,"name":"ARMENDARIX JUAN","tel":"2914432113","os":"PART","study":"DENTAL","cash":0,"card":0,"studyType":"radiografia","doctor":"Carla","date":"Mon Dec 12 2022 12:13:57 GMT-0300 (hora estándar de Argentina)","color":"dami"},{"id":"_x04dnyhe968","number":381,"name":"CRUZ HELEN","tel":"2914426915","os":"SWISS","study":"DENTAL","cash":0,"card":0,"studyType":"radiografia","doctor":"Carla","date":"Mon Dec 12 2022 12:05:33 GMT-0300 (hora estándar de Argentina)","color":"dami"},{"id":"_vfjw4dby8ej","number":380,"name":"VIGOVICH MIRKO","tel":"2916448399","os":"MEDIFE","study":"ATM","cash":0,"card":0,"studyType":"radiografia","doctor":"Carla","date":"Mon Dec 12 2022 12:04:37 GMT-0300 (hora estándar de Argentina)","color":"dami"},{"id":"_0gu96raqcgt","number":379,"name":"FERNANDEZ TOMAS","tel":"2915227207","os":"OSDE","study":"TORAX F","cash":0,"card":0,"studyType":"radiografia","doctor":"Carla","date":"Mon Dec 12 2022 11:58:27 GMT-0300 (hora estándar de Argentina)","color":"sole"},{"id":"_n9eoxl2dkgl","number":378,"name":"DE BATTISTA YANINA","tel":"2914426386","os":"IOMA","study":"TORAX F LUMBAR F","cash":"1000","card":0,"studyType":"radiografia","doctor":"Carla","date":"Mon Dec 12 2022 11:46:56 GMT-0300 (hora estándar de Argentina)","color":"sole"},{"id":"_d1dmccikabh","number":377,"name":"TOURN ETHEL","tel":"2914290950","os":"UNS","study":"DENTAL ANTEPIE FYP RODILLAS FYP AXIAL MANO FYP","cash":"500","card":0,"studyType":"radiografia","doctor":"Carla","date":"Mon Dec 12 2022 11:43:29 GMT-0300 (hora estándar de Argentina)","color":"sole"},{"id":"_te08h8k6mk","number":376,"name":"URIZ SELVA","tel":"2914622458","os":"OSPATCA","study":"MNP TORAX FYP","cash":0,"card":"500","studyType":"radiografia","doctor":"Carla","date":"Mon Dec 12 2022 11:40:33 GMT-0300 (hora estándar de Argentina)","color":"sole"},{"id":"_zvr0e9jwuo","number":375,"name":"MAQUEZ DANIEL","tel":"4543400","os":"FEDERADA","study":"DENTAL","cash":0,"card":"500","studyType":"radiografia","doctor":"Carla","date":"Mon Dec 12 2022 11:37:31 GMT-0300 (hora estándar de Argentina)","color":"dami"},{"id":"_dr2m2gnkguj","number":374,"name":"FERRER JUAN","tel":"2914654126","os":"PART","study":"DENTAL","cash":"2300","card":0,"studyType":"radiografia","doctor":"Carla","date":"Mon Dec 12 2022 11:29:47 GMT-0300 (hora estándar de Argentina)","color":"dami"},{"id":"_gmt9f5ssj5","number":373,"name":"MORDEGLIA MAURO","tel":"2915249968","os":"PART","study":"DENTAL","cash":"2300","card":0,"studyType":"radiografia","doctor":"Carla","date":"Mon Dec 12 2022 11:28:25 GMT-0300 (hora estándar de Argentina)","color":"dami"},{"id":"_lhy186qhhxj","number":372,"name":"CAMPETELLA GRACIELA","tel":"2914414676","os":"PART","study":"TOMOGRAFIA 48/41","cash":"3900","card":0,"studyType":"radiografia","doctor":"Carla","date":"Mon Dec 12 2022 11:25:42 GMT-0300 (hora estándar de Argentina)","color":"dami"},{"id":"_7ns3blomazc","number":371,"name":"LONDA JAVIER","tel":"2914057345","os":"UNS","study":"TORAX F","cash":"500","card":0,"studyType":"radiografia","doctor":"Carla","date":"Mon Dec 12 2022 11:15:54 GMT-0300 (hora estándar de Argentina)","color":"sole"},{"id":"_q4l0tx7vko","number":370,"name":"BRAY SILVINA","tel":"2914312445","os":"PART","study":"LUMBAR P","cash":"1700","card":0,"studyType":"radiografia","doctor":"Carla","date":"Mon Dec 12 2022 11:10:09 GMT-0300 (hora estándar de Argentina)","color":"noe"},{"id":"_pa2xqztmcyi","number":369,"name":"COPPA MARTINA","tel":"2915040380","os":"PART","study":"TOMOGRAFIA ATM","cash":"8900","card":0,"studyType":"radiografia","doctor":"Carla","date":"Mon Dec 12 2022 11:07:15 GMT-0300 (hora estándar de Argentina)","color1":"red","color":"dami"},{"id":"_5tzf20y0e3x","number":368,"name":"MALLIA LUCAS","tel":"2915278044","os":"PATRONES","study":"DENTAL","cash":"500","card":0,"studyType":"radiografia","doctor":"Carla","date":"Mon Dec 12 2022 11:06:00 GMT-0300 (hora estándar de Argentina)","color":"dami"},{"id":"_3s0wqs2jeai","number":367,"name":"SACKS FEDERICO","tel":"2914737390","os":"UNS","study":"HUESO PROPIO NARIS","cash":0,"card":0,"studyType":"radiografia","doctor":"Carla","date":"Mon Dec 12 2022 11:02:32 GMT-0300 (hora estándar de Argentina)","color":"sole"},{"id":"_if71e4qskrc","number":366,"name":"LLANCUFIL MICAELA","tel":"2920551253","os":"PART","study":"DENTAL","cash":"2300","card":0,"studyType":"radiografia","doctor":"Carla","date":"Mon Dec 12 2022 10:54:46 GMT-0300 (hora estándar de Argentina)","color":"dami"},{"id":"_esm1kxyur8f","number":365,"name":"LINNIG ALMA","tel":"29261545805","os":"IOMA","study":"DENTAL","cash":"800","card":0,"studyType":"radiografia","doctor":"Carla","date":"Mon Dec 12 2022 10:53:46 GMT-0300 (hora estándar de Argentina)","color":"dami"},{"id":"_jvrg93dw0lp","number":364,"name":"LOPINI MARCIANA","tel":"4446098","os":"PART","study":"DENTAL","cash":"2000","card":0,"studyType":"radiografia","doctor":"Carla","date":"Mon Dec 12 2022 10:52:26 GMT-0300 (hora estándar de Argentina)","color":"dami"},{"id":"_dtij38ai8il","number":363,"name":"STARC LOLA","tel":"2914264032","os":"IOMA","study":"DENTAL TELE ATM CEFALO","cash":0,"card":"6200","studyType":"radiografia","doctor":"Carla","date":"Mon Dec 12 2022 10:48:43 GMT-0300 (hora estándar de Argentina)","color1":"yellow","color":"dami"},{"id":"_rsbnb4i5k3g","number":362,"name":"CAPUZZO SILVIA","tel":"2914430949","os":"IOMA","study":"DENTAL","cash":"800","card":0,"studyType":"radiografia","doctor":"Carla","date":"Mon Dec 12 2022 10:46:35 GMT-0300 (hora estándar de Argentina)","color":"dami"},{"id":"_ayxx6dtg0nt","number":361,"name":"MARCHESSI TESSA","tel":"2914075106","os":"UNS","study":"DENTAL","cash":0,"card":0,"studyType":"radiografia","doctor":"Carla","date":"Mon Dec 12 2022 10:45:27 GMT-0300 (hora estándar de Argentina)","color":"dami"},{"id":"_qlcbxruylm","number":360,"name":"DIACO FRANCO","tel":"2914199578","os":"IOMA","study":"DENTAL","cash":"800","card":0,"studyType":"radiografia","doctor":"Carla","date":"Mon Dec 12 2022 10:43:38 GMT-0300 (hora estándar de Argentina)","color":"dami"},{"id":"_4g1s2dlbqpb","number":359,"name":"LAXAGUE BERNARDO","tel":"2914224588","os":"OSDE","study":"TORAX FYP","cash":0,"card":0,"studyType":"radiografia","doctor":"Carla","date":"Mon Dec 12 2022 10:42:45 GMT-0300 (hora estándar de Argentina)","color":"sole"},{"id":"_pjdsjit4ssr","number":358,"name":"YEFILAF ULISES","tel":"2914022049","os":"PART","study":"DENTAL","cash":"2300","card":0,"studyType":"radiografia","doctor":"Carla","date":"Mon Dec 12 2022 10:38:07 GMT-0300 (hora estándar de Argentina)","color":"dami"},{"id":"_kga6uge2lh","number":357,"name":"SCHELL JUAN","tel":"2914313131","os":"PAMI","study":"RODILLAS FYP","cash":"500","card":0,"studyType":"radiografia","doctor":"Carla","date":"Mon Dec 12 2022 10:34:16 GMT-0300 (hora estándar de Argentina)","color":"sole"},{"id":"_ges3fyy8ino","number":356,"name":"GAMDOLFO OLGA","tel":"2914271215","os":"PART","study":"DENTAL","cash":"2300","card":0,"studyType":"radiografia","doctor":"Carla","date":"Mon Dec 12 2022 10:26:59 GMT-0300 (hora estándar de Argentina)","color":"dami"},{"id":"_y02q5uqg9x","number":355,"name":"CHAMORRO JEREMIAS","tel":"2914410658","os":"PART","study":"DENTAL","cash":"2300","card":0,"studyType":"radiografia","doctor":"Carla","date":"Mon Dec 12 2022 10:21:39 GMT-0300 (hora estándar de Argentina)","color":"dami"},{"id":"_n8pc2trbhmh","number":354,"name":"PELAEZ HORACIO","tel":"4166217","os":"IOMA","study":"DENTAL","cash":"800","card":0,"studyType":"radiografia","doctor":"Carla","date":"Mon Dec 12 2022 10:20:11 GMT-0300 (hora estándar de Argentina)","color":"dami"},{"id":"_a4vr77ynh0p","number":353,"name":"DURAN AMPARO","tel":"2916438961","os":"PART","study":"DENTAL","cash":"2300","card":0,"studyType":"radiografia","doctor":"Carla","date":"Mon Dec 12 2022 10:17:19 GMT-0300 (hora estándar de Argentina)","color":"dami"},{"id":"_k404dfraef","number":352,"name":"GALLI VENECIA","tel":"2915272053","os":"OSMATA","study":"TORAX F","cash":"500","card":0,"studyType":"radiografia","doctor":"Carla","date":"Mon Dec 12 2022 10:08:37 GMT-0300 (hora estándar de Argentina)","color":"sole"},{"id":"_s7hcf9r2i78","number":351,"name":"LOZANO ANGELITA","tel":"2916431635","os":"PART","study":"DENTAL","cash":"2000","card":0,"studyType":"radiografia","doctor":"Carla","date":"Mon Dec 12 2022 09:47:49 GMT-0300 (hora estándar de Argentina)","color":"dami"},{"id":"_v0axzzh0gy9","number":350,"name":"MENDEZ LAUTARO","tel":"2914310693","os":"IOMA","study":"ESPINO F","cash":0,"card":"1000","studyType":"radiografia","doctor":"Carla","date":"Mon Dec 12 2022 09:44:54 GMT-0300 (hora estándar de Argentina)","color":"dami"},{"id":"_1xzzfzkvgv","number":348,"name":"AMUSO JOSE","tel":"23244692340","os":"BCO P","study":"HOMBRO FYP","cash":"500","card":0,"studyType":"radiografia","doctor":"Carla","date":"Mon Dec 12 2022 09:33:37 GMT-0300 (hora estándar de Argentina)","color":"sole"},{"id":"_y0gztte5oiq","number":347,"name":"HOFFMAN MARIA","tel":"4538790","os":"UNS","study":"PIE FYP O","cash":"500","card":0,"studyType":"radiografia","doctor":"Carla","date":"Mon Dec 12 2022 09:32:17 GMT-0300 (hora estándar de Argentina)","color":"sole"},{"id":"_z51u3qjo1dn","number":346,"name":"TRELLINI MARIANO","tel":"2914700717","os":"PART","study":"DENTAL","cash":"2300","card":0,"studyType":"radiografia","doctor":"Carla","date":"Mon Dec 12 2022 09:30:53 GMT-0300 (hora estándar de Argentina)","color":"noe"},{"id":"_xh18q9yc7r","number":345,"name":"MIRAMONTE FEDERICO","tel":"2914141681","os":"OSPATCA","study":"CODO FYP","cash":"500","card":0,"studyType":"radiografia","doctor":"Carla","date":"Mon Dec 12 2022 09:30:16 GMT-0300 (hora estándar de Argentina)","color":"sole"},{"id":"_ze2bysq3xyq","number":344,"name":"RIVERA MARIA","tel":"2915112270","os":"IOMA","study":"DENTAL","cash":0,"card":"800","studyType":"radiografia","doctor":"Carla","date":"Mon Dec 12 2022 09:27:42 GMT-0300 (hora estándar de Argentina)","color":"sole"},{"id":"_s1hmt4nv87i","number":343,"name":"VALDOVINO MARCELO","tel":"2914050710","os":"IOMA","study":"DENTAL","cash":"800","card":0,"studyType":"radiografia","doctor":"Carla","date":"Mon Dec 12 2022 09:25:49 GMT-0300 (hora estándar de Argentina)","color":"sole"},{"id":"_hy26rjg6m59","number":342,"name":"DI PIETRO HECTOR","tel":"2914163694","os":"DOSEM","study":"RODILLAS FYP ","cash":"500","card":0,"studyType":"radiografia","doctor":"Carla","date":"Mon Dec 12 2022 09:22:30 GMT-0300 (hora estándar de Argentina)","color":"sole","color1":"white"},{"id":"_41h3azkyty5","number":341,"name":"CALVO ALEJANDRA","tel":"2916414635","os":"IOMA","study":"MUÑECA FYP FEMUR FYP","cash":"1000","card":0,"studyType":"radiografia","doctor":"Carla","date":"Mon Dec 12 2022 09:19:40 GMT-0300 (hora estándar de Argentina)","color":"sole","color1":"white"},{"id":"_t7ogc5f7rcl","number":340,"name":"QUINTEROS ALICIA","tel":"2914680361","os":"OSDE","study":"TOMOGRAFIA 45-46-46","cash":0,"card":"3900","studyType":"radiografia","doctor":"Carla","date":"Mon Dec 12 2022 09:15:36 GMT-0300 (hora estándar de Argentina)","color":"noe","color1":"red"},{"id":"_ys89r6txmon","number":339,"name":" TINERVIA OSCAR","tel":"2915014346","os":"IOMA","study":"DENTAL","cash":0,"card":"800","studyType":"radiografia","doctor":"Carla","date":"Mon Dec 12 2022 09:13:03 GMT-0300 (hora estándar de Argentina)","color":"noe"},{"id":"_khrf12903p9","number":338,"name":"MARCHETTI BLANCA","tel":"2914273614","os":"PAMI","study":"HOMBRO FYP","cash":"500","card":0,"studyType":"radiografia","doctor":"Carla","date":"Mon Dec 12 2022 09:10:03 GMT-0300 (hora estándar de Argentina)","color":"sole"},{"id":"_hyoc5lgps9q","number":337,"name":"SOTO NANCY","tel":"2914472023","os":"UOM","study":"RODILLA DER FYP AXIAL 30-60-90","cash":0,"card":0,"studyType":"radiografia","doctor":"Carla","date":"Mon Dec 12 2022 09:04:03 GMT-0300 (hora estándar de Argentina)","color":"sole"},{"id":"_9uhv6d8s26l","number":336,"name":"HERMAN ESTER","tel":"2915704923","os":"PART","study":"DENTAL","cash":"2000","card":0,"studyType":"radiografia","doctor":"Carla","date":"Mon Dec 12 2022 09:01:39 GMT-0300 (hora estándar de Argentina)","color":"noe"},{"id":"_xz9606efze","number":335,"name":"PEREYRA SUSANA","tel":"2915263735","os":"IOMA","study":"LUMBAR FYP PELVIS RODILLAS FYP MONOP","cash":"1500","card":0,"studyType":"radiografia","doctor":"Carla","date":"Mon Dec 12 2022 09:00:06 GMT-0300 (hora estándar de Argentina)","color":"sole"},{"id":"_abpy3xciq0g","number":334,"name":"THEMTHAM LINA","tel":"2914470124","os":"IOMA","study":"DENTAL","cash":"800","card":0,"studyType":"radiografia","doctor":"Carla","date":"Mon Dec 12 2022 08:58:42 GMT-0300 (hora estándar de Argentina)","color":"sole"},{"id":"_p6n8t9v3wr","number":333,"name":"SANHUEZA GLADYS","tel":"2914063580","os":"PART","study":"DENTAL","cash":"2300","card":0,"studyType":"radiografia","doctor":"Carla","date":"Mon Dec 12 2022 08:56:30 GMT-0300 (hora estándar de Argentina)","color":"sole"},{"id":"_sr1dv2l4sg8","number":332,"name":"CAMPOS MARIA INES","tel":"2914124826","os":"PART","study":"DENTAL","cash":"2300","card":0,"studyType":"radiografia","doctor":"Carla","date":"Mon Dec 12 2022 08:56:01 GMT-0300 (hora estándar de Argentina)","color":"sole"}]