[{"id":"_4e6e9axiyw5","number":400,"name":"PIÑA ANA","tel":"2915702370","os":"IOMA","study":"DENTAL","cash":"800","card":0,"studyType":"radiografia","doctor":"Carla","date":"Thu Sep 22 2022 19:04:28 GMT-0300 (hora estándar de Argentina)","color":"alicia"},{"id":"_5tc0nerp0gx","number":399,"name":"OTT GABRIELA","tel":"154230057","os":"IOMA","study":"TOBILLO Y PIE F Y P","cash":"1500","card":0,"studyType":"radiografia","doctor":"Carla","date":"Thu Sep 22 2022 19:01:48 GMT-0300 (hora estándar de Argentina)","color":"alicia"},{"id":"_hz93s7hx2yl","number":398,"name":"MARINI FABIAN","tel":"2914631093","os":"UNS","study":"DENTAL","cash":"300","card":0,"studyType":"radiografia","doctor":"Carla","date":"Thu Sep 22 2022 18:34:05 GMT-0300 (hora estándar de Argentina)","color":"alicia"},{"id":"_cindags8ht9","number":397,"name":"ELIZALDE ENZO","tel":"2915782252","os":"PART","study":"DENTAL","cash":"2300","card":0,"studyType":"radiografia","doctor":"Carla","date":"Thu Sep 22 2022 18:33:03 GMT-0300 (hora estándar de Argentina)","color":"alicia"},{"id":"_yc5gcghr99p","number":396,"name":"HERAS ARIEL","tel":"2920575448","os":"PART","study":"DENTAL","cash":"2300","card":0,"studyType":"radiografia","doctor":"Carla","date":"Thu Sep 22 2022 18:11:59 GMT-0300 (hora estándar de Argentina)","color":"carmen"},{"id":"_h2d1n77o7c5","number":395,"name":"GAUNA CAMILA","tel":"2916461849","os":"AVALIAN","study":"TOBILLO IZQ F, P","cash":"300","card":0,"studyType":"radiografia","doctor":"Carla","date":"Thu Sep 22 2022 17:56:57 GMT-0300 (hora estándar de Argentina)","color":"alicia"},{"id":"_19h4vrgr262","number":394,"name":"FERNANDEZ ANGELINA","tel":"2914062482","os":"PART","study":"DENTAL","cash":"2300","card":0,"studyType":"radiografia","doctor":"Carla","date":"Thu Sep 22 2022 17:55:29 GMT-0300 (hora estándar de Argentina)","color":"alicia"},{"id":"_gobeh49s806","number":393,"name":"MARTINEZ DELIA","tel":"2914041987","os":"IOMA","study":"TORAX F, P","cash":"1000","card":0,"studyType":"radiografia","doctor":"Carla","date":"Thu Sep 22 2022 17:53:21 GMT-0300 (hora estándar de Argentina)","color":"carmen"},{"id":"_1f32qrrxd1x","number":392,"name":"FERNANDEZ JOAQUIN","tel":"2918036935","os":"PART","study":"DENTAL","cash":0,"card":"2300","studyType":"radiografia","doctor":"Carla","date":"Thu Sep 22 2022 17:50:02 GMT-0300 (hora estándar de Argentina)","color":"alicia"},{"id":"_bugn9rhd90g","number":391,"name":"HEGEL AGUSTIN","tel":"2914253519","os":"SWISS","study":"CAVUM P","cash":0,"card":0,"studyType":"radiografia","doctor":"Carla","date":"Thu Sep 22 2022 17:45:33 GMT-0300 (hora estándar de Argentina)","color":"alicia"},{"id":"_2k6l4r1nqwr","number":390,"name":"SCHECHTEL LUDMILA","tel":"2914195486","os":"OMINT","study":"ESPINO F, P","cash":0,"card":0,"studyType":"radiografia","doctor":"Carla","date":"Thu Sep 22 2022 17:31:34 GMT-0300 (hora estándar de Argentina)","color":"carmen"},{"id":"_zi85p8fxr88","number":389,"name":"MELINGER BERNARDITA","tel":"2920261610","os":"OSDE","study":"DEMTAL","cash":0,"card":0,"studyType":"radiografia","doctor":"Carla","date":"Thu Sep 22 2022 17:30:17 GMT-0300 (hora estándar de Argentina)","color":"carmen"},{"id":"_9gxp3ivurzr","number":388,"name":"DISTEL EMMA","tel":"2914167217","os":"UNS","study":"DENTAL","cash":0,"card":0,"studyType":"radiografia","doctor":"Carla","date":"Thu Sep 22 2022 17:20:34 GMT-0300 (hora estándar de Argentina)","color":"carmen"},{"id":"_flwj188fcfr","number":387,"name":"RASTELLI STELLA","tel":"2915265042","os":"IOMA","study":"TORAX F, P","cash":"1000","card":0,"studyType":"radiografia","doctor":"Carla","date":"Thu Sep 22 2022 17:01:58 GMT-0300 (hora estándar de Argentina)","color":"alicia"},{"id":"_2st38t9d28n","number":386,"name":"VILLVICENCIO CAMILA","tel":"2914677000","os":"UNS","study":"MUÑECA D F, P","cash":"300","card":0,"studyType":"radiografia","doctor":"Carla","date":"Thu Sep 22 2022 16:58:08 GMT-0300 (hora estándar de Argentina)","color":"carmen"},{"id":"_ljkbn7xxu2","number":385,"name":"LOPEZ MILAGROS","tel":"2915329183","os":"IOMA","study":"DENTAL","cash":"800","card":0,"studyType":"radiografia","doctor":"Carla","date":"Thu Sep 22 2022 16:55:05 GMT-0300 (hora estándar de Argentina)","color":"alicia"},{"id":"_9y3ceh114ou","number":384,"name":"YATZKY JOSIAN","tel":"2915741313","os":"SANCOR","study":"DENTAL","cash":0,"card":"300","studyType":"radiografia","doctor":"Carla","date":"Thu Sep 22 2022 16:52:14 GMT-0300 (hora estándar de Argentina)","color":"alicia"},{"id":"_dmx8yiw0fh9","number":383,"name":"MEDINA ALEGRIA","tel":"2914970550","os":"PART","study":"DENTAL","cash":0,"card":"2300","studyType":"radiografia","doctor":"Carla","date":"Thu Sep 22 2022 16:47:10 GMT-0300 (hora estándar de Argentina)","color":"alicia"},{"id":"_qcc6myevflr","number":382,"name":"ALBORNOZ SILVINA","tel":"28946539","os":"OSDE","study":"DENTAL","cash":0,"card":0,"studyType":"radiografia","doctor":"Carla","date":"Thu Sep 22 2022 16:45:48 GMT-0300 (hora estándar de Argentina)","color":"alicia"},{"id":"_rj6qgvc94fk","number":381,"name":"RODRIGUEZ THIAGO","tel":"2915325874","os":"PREVENCION","study":"DENTAL","cash":"300","card":0,"studyType":"radiografia","doctor":"Carla","date":"Thu Sep 22 2022 16:43:42 GMT-0300 (hora estándar de Argentina)","color":"alicia"},{"id":"_5fx13vksm94","number":380,"name":"OVIEDO JULIAN","tel":"2914050363","os":"PART","study":"CODO D F, P","cash":"1700","card":0,"studyType":"radiografia","doctor":"Carla","date":"Thu Sep 22 2022 16:39:56 GMT-0300 (hora estándar de Argentina)","color":"carmen"},{"id":"_haf4soto9tu","number":379,"name":"SACIDO MARIANO","tel":"2914232137","os":"UNS","study":"LUMB FERG, PELVIS F, P","cash":"300","card":0,"studyType":"radiografia","doctor":"Carla","date":"Thu Sep 22 2022 16:38:56 GMT-0300 (hora estándar de Argentina)","color":"carmen"},{"id":"_i1j8mfoqaw","number":378,"name":"SEQUEIRA MILAGROS","tel":"2914272887","os":"FEDERADA","study":"DENTAL","cash":"300","card":0,"studyType":"radiografia","doctor":"Carla","date":"Thu Sep 22 2022 16:37:36 GMT-0300 (hora estándar de Argentina)","color":"alicia"},{"id":"_nfyqgdf7hmf","number":377,"name":"POGIOLI VICTOR","tel":"2916439419","os":"IOMA","study":"RODILLAS F, P, AXIAL","cash":"1600","card":0,"studyType":"radiografia","doctor":"Carla","date":"Thu Sep 22 2022 16:32:21 GMT-0300 (hora estándar de Argentina)","color":"carmen"},{"id":"_dmgr8fu1u1f","number":376,"name":"TEJADA CARINA","tel":"2914169872","os":"SWISS","study":"CODO D F, P","cash":0,"card":0,"studyType":"radiografia","doctor":"Carla","date":"Thu Sep 22 2022 16:23:47 GMT-0300 (hora estándar de Argentina)","color":"carmen"},{"id":"_tg3pblwuay","number":375,"name":"SCHNEIDER VALENTINA","tel":"2914052497","os":"FEDERADA","study":"DEDO MAYOR MANO IZQ F, P","cash":"300","card":0,"studyType":"radiografia","doctor":"Carla","date":"Thu Sep 22 2022 16:22:00 GMT-0300 (hora estándar de Argentina)","color":"alicia"},{"id":"_cv7mr0nzyv6","number":374,"name":"MUÑOZ SERGIO","tel":"2914411659","os":"PART","study":"TOMO PIEZAS 42,41,31,32","cash":"2900","card":0,"studyType":"radiografia","doctor":"Carla","date":"Thu Sep 22 2022 16:19:22 GMT-0300 (hora estándar de Argentina)","color1":"red","color":"alicia"},{"id":"_qpdnvmd1z0f","number":373,"name":"DILSCHNEIDER BRENDA","tel":"155029782","os":"PART","study":"DENTAL","cash":"2300","card":0,"studyType":"radiografia","doctor":"Carla","date":"Thu Sep 22 2022 16:16:54 GMT-0300 (hora estándar de Argentina)","color":"carmen"},{"id":"_f00o68gll8c","number":372,"name":"HIGUERA KARINA","tel":"155042662","os":"OSCHOCA","study":"DENTAL","cash":0,"card":0,"studyType":"radiografia","doctor":"Carla","date":"Thu Sep 22 2022 16:15:32 GMT-0300 (hora estándar de Argentina)","color":"carmen"},{"id":"_af5xesshiz","number":371,"name":"PASTENES JAZMIN","tel":"2914385837","os":"OSPECON","study":"PIE IZQ F, P","cash":"1700","card":0,"studyType":"radiografia","doctor":"Carla","date":"Thu Sep 22 2022 15:57:12 GMT-0300 (hora estándar de Argentina)","color":"alicia"},{"id":"_g80sjkd32ni","number":370,"name":"REALE MARA","tel":"2915265600","os":"OSDE","study":"MNP, FNP","cash":0,"card":0,"studyType":"radiografia","doctor":"Carla","date":"Thu Sep 22 2022 15:52:06 GMT-0300 (hora estándar de Argentina)","color":"alicia"},{"id":"_t2ano8tfozr","number":369,"name":"SANCHEZ DANIELA","tel":"2914187392","os":"IOMA","study":"TORAX F","cash":"800","card":0,"studyType":"radiografia","doctor":"Carla","date":"Thu Sep 22 2022 15:28:33 GMT-0300 (hora estándar de Argentina)","color":"carmen","color1":"white"},{"id":"_5hxagahlt37","number":368,"name":"ROMANO JULIA","tel":"2932492825","os":"IOMA","study":"COL DL F, P","cash":"1000","card":0,"studyType":"radiografia","doctor":"Carla","date":"Thu Sep 22 2022 15:20:49 GMT-0300 (hora estándar de Argentina)","color":"alicia"},{"id":"_eipf1djrugf","number":367,"name":"OÑATE CAMILA","tel":"2984936786","os":"PART","study":"DENTAL","cash":0,"card":"2300","studyType":"radiografia","doctor":"Carla","date":"Thu Sep 22 2022 15:17:10 GMT-0300 (hora estándar de Argentina)","color":"carmen"},{"id":"_xzmyou8iys","number":366,"name":"OROS NELLI","tel":"2954943566","os":"SWIS","study":"DENTAL","cash":0,"card":0,"studyType":"radiografia","doctor":"Carla","date":"Thu Sep 22 2022 15:16:20 GMT-0300 (hora estándar de Argentina)","color":"carmen"},{"id":"_xafynt1uh1r","number":365,"name":"PIERINI SANTIAGO","tel":"2915222043","os":"PART","study":"PIE IZQ F, P, O","cash":"3000","card":0,"studyType":"radiografia","doctor":"Carla","date":"Thu Sep 22 2022 15:11:47 GMT-0300 (hora estándar de Argentina)","color":"alicia"},{"id":"_z2l7mbsu9eg","number":364,"name":"JORDAN FRANCISCO","tel":"2915352446","os":"UNS","study":"DENTAL","cash":0,"card":0,"studyType":"radiografia","doctor":"Carla","date":"Thu Sep 22 2022 15:10:24 GMT-0300 (hora estándar de Argentina)","color":"carmen"},{"id":"_v3b4lheencl","number":363,"name":"REYNAFE ALBERTO","tel":"2915356453","os":"PAMI","study":"RODILLAS F, P","cash":"500","card":0,"studyType":"radiografia","doctor":"Carla","date":"Thu Sep 22 2022 15:09:10 GMT-0300 (hora estándar de Argentina)","color":"alicia"},{"id":"_hf45j4ash7t","number":362,"name":"giraudo alejandro","tel":"2914275759","os":"MEDIFE","study":"torax f, p","cash":0,"card":0,"studyType":"radiografia","doctor":"Carla","date":"Thu Sep 22 2022 15:03:50 GMT-0300 (hora estándar de Argentina)","color":"carmen"},{"id":"_n1actx0g9zr","number":361,"name":"corn alberto","tel":"2916443344","os":"part","study":"dental","cash":"1600","card":0,"studyType":"radiografia","doctor":"Carla","date":"Thu Sep 22 2022 14:54:47 GMT-0300 (hora estándar de Argentina)","color":"carmen"},{"id":"_wev3dlxwj1c","number":360,"name":"CLEMENTE ROMINA","tel":"2915744079","os":"MEDIFE","study":"TORAX F, P","cash":0,"card":0,"studyType":"radiografia","doctor":"Carla","date":"Thu Sep 22 2022 14:10:11 GMT-0300 (hora estándar de Argentina)","color":"dami"},{"id":"_8vd5s5avx1","number":359,"name":"HERROU PEDRO","tel":"2915661616","os":"UNS","study":"DENTAL","cash":0,"card":0,"studyType":"radiografia","doctor":"Carla","date":"Thu Sep 22 2022 13:58:16 GMT-0300 (hora estándar de Argentina)","color":"dami"},{"id":"_3pipbva5d4l","number":358,"name":"MALAN JUAN","tel":"291405404","os":"OSDE","study":"TORAX F, P, MNP, FNP,","cash":0,"card":0,"studyType":"radiografia","doctor":"Carla","date":"Thu Sep 22 2022 13:55:46 GMT-0300 (hora estándar de Argentina)","color":"carmen"},{"id":"_1a6v7g7ruxr","number":357,"name":"ARANA ROCIO","tel":"2804613383","os":"IOMA","study":"DENTAL","cash":"800","card":0,"studyType":"radiografia","doctor":"Carla","date":"Thu Sep 22 2022 13:43:23 GMT-0300 (hora estándar de Argentina)","color":"carmen"},{"id":"_pey6z1utczr","number":356,"name":"CAPPELLETTI MARIA","tel":"2914057144","os":"AVALIAN","study":"PIE IZQ F, P EST, O","cash":"300","card":0,"studyType":"radiografia","doctor":"Carla","date":"Thu Sep 22 2022 13:37:55 GMT-0300 (hora estándar de Argentina)","color":"dami"},{"id":"_vj1ayxapuq8","number":355,"name":"CANCHELARA CLAUDIA ELISABET","tel":"2915043939","os":"IOMA","study":"SPN","cash":"0","card":"800","studyType":"radiografia","doctor":"Carla","date":"Thu Sep 22 2022 13:24:29 GMT-0300 (hora estándar de Argentina)","color":"dami"},{"id":"_sxppjakte2","number":354,"name":" MITILLI SOFIA MABEL","tel":"2916492791","os":"IOMA","study":"TORAX F Y P","cash":"1000","card":0,"studyType":"radiografia","doctor":"Carla","date":"Thu Sep 22 2022 13:22:49 GMT-0300 (hora estándar de Argentina)","color":"dami"},{"id":"_ll5n6kwsgc","number":353,"name":"PULION VALENTINA","tel":"02920618598","os":"MEDIFE","study":"CADERAS F","cash":0,"card":0,"studyType":"radiografia","doctor":"Carla","date":"Thu Sep 22 2022 13:21:20 GMT-0300 (hora estándar de Argentina)","color":"noe"},{"id":"_urlfxc1o9nc","number":352,"name":"LEIROS ANALIA","tel":"2914375841","os":"SANIDAD","study":"DENTAL","cash":0,"card":0,"studyType":"radiografia","doctor":"Carla","date":"Thu Sep 22 2022 12:47:02 GMT-0300 (hora estándar de Argentina)","color":"noe"},{"id":"_z7xqnyz0e7p","number":351,"name":"CAMPI MARIA EMILIA","tel":"2914067822","os":"IOMA","study":"DENTAL","cash":0,"card":"800","studyType":"radiografia","doctor":"Carla","date":"Thu Sep 22 2022 12:35:24 GMT-0300 (hora estándar de Argentina)","color":"sole"},{"id":"_xwkgo76ua6h","number":350,"name":"CAMPI JUAN PABLO","tel":"2914067822","os":"IOMA","study":"DENTAL","cash":0,"card":"800","studyType":"radiografia","doctor":"Carla","date":"Thu Sep 22 2022 12:33:13 GMT-0300 (hora estándar de Argentina)","color":"sole"},{"id":"_3ibnngzgzk4","number":349,"name":"MARTI MABEL","tel":"2915012725","os":"SWISS","study":"DENTAL Y ATM","cash":0,"card":0,"studyType":"radiografia","doctor":"Carla","date":"Thu Sep 22 2022 12:31:29 GMT-0300 (hora estándar de Argentina)","color":"sole"},{"id":"_uzepz7j1rr","number":348,"name":"MILOZZI ADRIANA BEATRIZ","tel":"2914056335","os":"OSDE","study":"TORAX F Y P,MNP, FNP","cash":0,"card":0,"studyType":"radiografia","doctor":"Carla","date":"Thu Sep 22 2022 12:27:43 GMT-0300 (hora estándar de Argentina)","color":"noe"},{"id":"_04ea7cvcn0qo","number":347,"name":"ALLERBORN JUAN IGNACIO","tel":"29164292729","os":"UNS","study":"DENTAL","cash":0,"card":0,"studyType":"radiografia","doctor":"Carla","date":"Thu Sep 22 2022 12:18:10 GMT-0300 (hora estándar de Argentina)","color":"noe"},{"id":"_f9j0liftykn","number":346,"name":"SANTIN VIVIANA","tel":"2914377609","os":"MEDIFE","study":"CC F Y P","cash":0,"card":0,"studyType":"radiografia","doctor":"Carla","date":"Thu Sep 22 2022 12:15:35 GMT-0300 (hora estándar de Argentina)","color":"noe"},{"id":"_qnnyek557x","number":345,"name":"SPAGNUOLO JULIA","tel":"2914060569","os":"IOMA","study":"DENTAL (NP)","cash":"800","card":0,"studyType":"radiografia","doctor":"Carla","date":"Thu Sep 22 2022 12:02:41 GMT-0300 (hora estándar de Argentina)","color":"dami"},{"id":"_id5b7oh1k1c","number":344,"name":"CHIUCCARIELLO JOSEFINA","tel":"2914232425","os":"L Y F","study":"RODILLA Y CADERA D F Y P","cash":"300","card":0,"studyType":"radiografia","doctor":"Carla","date":"Thu Sep 22 2022 12:00:50 GMT-0300 (hora estándar de Argentina)","color":"noe"},{"id":"_04hg9rfokh94","number":343,"name":"CRISTEFF NORMA","tel":"291042311","os":"SWISS","study":"DENTAL","cash":0,"card":0,"studyType":"radiografia","doctor":"Carla","date":"Thu Sep 22 2022 11:58:59 GMT-0300 (hora estándar de Argentina)","color":"dami"},{"id":"_nyc16unxozi","number":342,"name":"REALE CARLOS","tel":"2914195791","os":"UNS","study":"TOMO MAX SUP","cash":0,"card":0,"studyType":"radiografia","doctor":"Carla","date":"Thu Sep 22 2022 11:46:34 GMT-0300 (hora estándar de Argentina)","color1":"red","color":"dami"},{"id":"_c1hgvrg022r","number":341,"name":"FIDANI ESTEFANIA","tel":"291572927260","os":"DASUTEN","study":"DENTAL (NP)","cash":0,"card":0,"studyType":"radiografia","doctor":"Carla","date":"Thu Sep 22 2022 11:36:55 GMT-0300 (hora estándar de Argentina)","color":"dami"},{"id":"_wpph1z71hwl","number":340,"name":"SALAZAR FRANCISCO","tel":"2915137579","os":"PREVENCION","study":"DENTAL","cash":"300","card":0,"studyType":"radiografia","doctor":"Carla","date":"Thu Sep 22 2022 11:30:57 GMT-0300 (hora estándar de Argentina)","color":"dami"},{"id":"_ibybbv5g9z","number":339,"name":"VERCESI OSCAR","tel":"2916421671","os":"UNS","study":"TORAX F Y P","cash":"300","card":0,"studyType":"radiografia","doctor":"Carla","date":"Thu Sep 22 2022 11:28:14 GMT-0300 (hora estándar de Argentina)","color":"noe"},{"id":"_7adbwdn34sx","number":338,"name":"HOLZMANN SANDRA MARINA","tel":"2923459999","os":"IOMA","study":"DENTAL","cash":"800","card":0,"studyType":"radiografia","doctor":"Carla","date":"Thu Sep 22 2022 11:17:51 GMT-0300 (hora estándar de Argentina)","color":"dami"},{"id":"_ojva90b7fyf","number":337,"name":"SCHIAVONI SOFIA EMILIA","tel":"2914162406","os":"IOMA","study":"DENTAL","cash":"800","card":0,"studyType":"radiografia","doctor":"Carla","date":"Thu Sep 22 2022 11:10:23 GMT-0300 (hora estándar de Argentina)","color":"dami"},{"id":"_trnar5ic1hc","number":336,"name":"VILLARROEL CARLOS","tel":"1167879898","os":"PART","study":"DENTAL","cash":"1600","card":0,"studyType":"radiografia","doctor":"Carla","date":"Thu Sep 22 2022 11:08:37 GMT-0300 (hora estándar de Argentina)","color":"dami"},{"id":"_ldspgz3uhle","number":335,"name":"VILLARREAL MARIA ALICIA","tel":"2914725863","os":"IOMA","study":"TORAX F","cash":"800","card":0,"studyType":"radiografia","doctor":"Carla","date":"Thu Sep 22 2022 10:51:14 GMT-0300 (hora estándar de Argentina)","color":"noe"},{"id":"_g6syp8tx2o9","number":334,"name":"MANRRESSA LILIANA","tel":"2914621618","os":"PART","study":"DENTAL","cash":"1600","card":0,"studyType":"radiografia","doctor":"Carla","date":"Thu Sep 22 2022 10:49:33 GMT-0300 (hora estándar de Argentina)","color":"dami"},{"id":"_qt66n0o7dra","number":333,"name":"BLANCATO CECILIA","tel":"2914234709","os":"FEDERADA","study":"ESPINO F Y P","cash":"300","card":0,"studyType":"radiografia","doctor":"Carla","date":"Thu Sep 22 2022 10:44:37 GMT-0300 (hora estándar de Argentina)","color":"dami"},{"id":"_1rgrqm3i6hc","number":332,"name":"ANRIQUE AGUSTINA","tel":"2914182825","os":"DOSEM","study":"DENTAL","cash":"300","card":0,"studyType":"radiografia","doctor":"Carla","date":"Thu Sep 22 2022 10:37:43 GMT-0300 (hora estándar de Argentina)","color":"dami"},{"id":"_iezeo1zwk5g","number":331,"name":"ETMAN MARIA VICTORIA","tel":"2914497700","os":"OSDEIPP","study":"MNP, FNP, TORAX","cash":"300","card":0,"studyType":"radiografia","doctor":"Carla","date":"Thu Sep 22 2022 10:35:59 GMT-0300 (hora estándar de Argentina)","color":"noe"},{"id":"_qfu859ozet","number":330,"name":"CASTIGLIONI BENJAMIN","tel":"2281402760","os":"UOM","study":"CODO IZQ F","cash":0,"card":0,"studyType":"radiografia","doctor":"Carla","date":"Thu Sep 22 2022 10:29:12 GMT-0300 (hora estándar de Argentina)","color":"sole"},{"id":"_ik9t7wlgssn","number":329,"name":"QUIROZ SIOMARA","tel":"292543931","os":"PART","study":"DENTAL","cash":0,"card":"1600","studyType":"radiografia","doctor":"Carla","date":"Thu Sep 22 2022 10:24:59 GMT-0300 (hora estándar de Argentina)","color":"dami"},{"id":"_sh46n21ckbf","number":328,"name":"CABRERA MARIA SOLEDAD","tel":"2915661856","os":"SANIDAD","study":"DENTAL","cash":0,"card":0,"studyType":"radiografia","doctor":"Carla","date":"Thu Sep 22 2022 10:23:12 GMT-0300 (hora estándar de Argentina)","color":"dami"},{"id":"_v1hz0u4vcv","number":327,"name":"STREITENBERGER ANA","tel":"2915025075","os":"PART","study":"TORAX F","cash":"1400","card":0,"studyType":"radiografia","doctor":"Carla","date":"Thu Sep 22 2022 10:19:47 GMT-0300 (hora estándar de Argentina)","color":"noe"},{"id":"_r4bgt9o1uxo","number":326,"name":"SEDANO ANA MARIA","tel":"2914161884","os":"MEDIFE","study":"TORAX F Y PIE D F Y P","cash":0,"card":0,"studyType":"radiografia","doctor":"Carla","date":"Thu Sep 22 2022 10:18:35 GMT-0300 (hora estándar de Argentina)","color":"noe"},{"id":"_6qog9n254cj","number":325,"name":"ANFOSSI MARCOS","tel":"2914075298","os":"UNS","study":"DL F Y P","cash":"300","card":0,"studyType":"radiografia","doctor":"Carla","date":"Thu Sep 22 2022 10:13:06 GMT-0300 (hora estándar de Argentina)","color":"noe"},{"id":"_rjyt8fmarbc","number":324,"name":"RODRIGUEZ ELDA ESTHER","tel":"2914757367","os":"IOMA","study":"DENTAL","cash":"800","card":0,"studyType":"radiografia","doctor":"Carla","date":"Thu Sep 22 2022 10:11:28 GMT-0300 (hora estándar de Argentina)","color":"noe"},{"id":"_byjroowlc09","number":323,"name":"SANTUCH JOSE LUIS","tel":"2914254419","os":"PAMI","study":"HOMBRO IZQ F, CODO IZQ F Y P, MUÑECA IZQ F Y P","cash":"300","card":0,"studyType":"radiografia","doctor":"Carla","date":"Thu Sep 22 2022 10:09:11 GMT-0300 (hora estándar de Argentina)","color":"noe"},{"id":"_mmf28rcur9o","number":322,"name":"CAMAÑO STELLA MARIS","tel":"2914660016","os":"IOMA","study":"DENTAL","cash":"800","card":0,"studyType":"radiografia","doctor":"Carla","date":"Thu Sep 22 2022 09:52:16 GMT-0300 (hora estándar de Argentina)","color":"noe"},{"id":"_df21ebquu1t","number":321,"name":"ROBLEDO AMBAR","tel":"2915744334","os":"FEDERADA","study":"TORAX","cash":"300","card":0,"studyType":"radiografia","doctor":"Carla","date":"Thu Sep 22 2022 09:33:09 GMT-0300 (hora estándar de Argentina)","color":"noe"},{"id":"_nsjae1fynaj","number":320,"name":"FERREYRO BRUNELLA","tel":"2914619302","os":"PART","study":"MNP, CAVUM","cash":"2400","card":0,"studyType":"radiografia","doctor":"Carla","date":"Thu Sep 22 2022 09:31:10 GMT-0300 (hora estándar de Argentina)","color":"noe"},{"id":"_c7svgvne81g","number":319,"name":"GIL SILVIA GRISELDA","tel":"2914225324","os":"PAMI","study":"RODILLA IZQ F Y P MONO","cash":"300","card":0,"studyType":"radiografia","doctor":"Carla","date":"Thu Sep 22 2022 09:28:10 GMT-0300 (hora estándar de Argentina)","color":"noe"},{"id":"_9o3verge8qw","number":318,"name":"VEGGI ANDREA","tel":"2915010607","os":"FEDERADA","study":"DENTAL","cash":"300","card":0,"studyType":"radiografia","doctor":"Carla","date":"Thu Sep 22 2022 09:20:05 GMT-0300 (hora estándar de Argentina)","color":"noe"},{"id":"_xdjbrxl3h9m","number":317,"name":"PASCUCCI GUILLERMO","tel":"2915714973","os":"TORAX","study":"TORAX","cash":0,"card":0,"studyType":"radiografia","doctor":"Carla","date":"Thu Sep 22 2022 09:11:03 GMT-0300 (hora estándar de Argentina)","color":"noe"},{"id":"_tmg37rh981e","number":316,"name":"MORIGGIA GABRIELA NORA","tel":"2914148682","os":"IOMA","study":"DENTAL","cash":"800","card":0,"studyType":"radiografia","doctor":"Carla","date":"Thu Sep 22 2022 09:04:28 GMT-0300 (hora estándar de Argentina)","color":"noe"},{"id":"_udjdthk3wy","number":315,"name":"MONTERO LEANDRO","tel":"2914296644","os":"PART","study":"MANOS Y MUÑECAS F Y P","cash":"3800","card":0,"studyType":"radiografia","doctor":"Carla","date":"Thu Sep 22 2022 08:59:20 GMT-0300 (hora estándar de Argentina)","color":"noe"}]