[
    {
        "id": "_h7mb1h7v4z",
        "number": 362,
        "name": "MERODIO FEDERICO ",
        "tel": "02932457429",
        "os": "UNO S",
        "study": "DENTAL",
        "cash": 0,
        "card": 0,
        "studyType": "radiografia",
        "doctor": "Carla",
        "date": "Thu Oct 06 2022 19:10:45 GMT-0300 (hora estándar de Argentina)",
        "color": "carmen"
    },
    {
        "id": "_7txudwnba8b",
        "number": 361,
        "name": "SISTI MANUELA",
        "tel": "2914373819",
        "os": "DASUTEN",
        "study": "ATM",
        "cash": "300",
        "card": 0,
        "studyType": "radiografia",
        "doctor": "Carla",
        "date": "Thu Oct 06 2022 19:04:38 GMT-0300 (hora estándar de Argentina)",
        "color": "carmen"
    },
    {
        "id": "_mcej0fexm3",
        "number": 360,
        "name": "BAUMGAERTNER MARIANELA",
        "tel": "2914654789",
        "os": "IOMA",
        "study": "DENTAL",
        "cash": "800",
        "card": 0,
        "studyType": "radiografia",
        "doctor": "Carla",
        "date": "Thu Oct 06 2022 18:47:12 GMT-0300 (hora estándar de Argentina)",
        "color": "carmen"
    },
    {
        "id": "_h57sizz9wv7",
        "number": 359,
        "name": "MUÑ IZ BULLRICH AZUL MARIA",
        "tel": "2914705185",
        "os": "OSDE",
        "study": "PIE D F, 3/4, DENTAL",
        "cash": 0,
        "card": 0,
        "studyType": "radiografia",
        "doctor": "Carla",
        "date": "Thu Oct 06 2022 18:32:37 GMT-0300 (hora estándar de Argentina)",
        "color": "carmen"
    },
    {
        "id": "_136fam7ob5o",
        "number": 358,
        "name": "FERNANDEZ MAURO",
        "tel": "2914713694",
        "os": "FEDERADA",
        "study": "DEDO INDICE D F, P EST",
        "cash": "300",
        "card": 0,
        "studyType": "radiografia",
        "doctor": "Carla",
        "date": "Thu Oct 06 2022 18:24:38 GMT-0300 (hora estándar de Argentina)",
        "color": "carmen"
    },
    {
        "id": "_leowbih8ys",
        "number": 357,
        "name": "HERRERA GABRIELA",
        "tel": "2916495957",
        "os": "UTA",
        "study": "HOMBRO D F, P",
        "cash": "300",
        "card": 0,
        "studyType": "radiografia",
        "doctor": "Carla",
        "date": "Thu Oct 06 2022 18:20:59 GMT-0300 (hora estándar de Argentina)",
        "color": "carmen"
    },
    {
        "id": "_wawybs0djea",
        "number": 356,
        "name": "GANCEDO LUCIO",
        "tel": "2916495957",
        "os": "UTA",
        "study": "HUESOS PROIOS NARIZ F, P, TORAX F,P",
        "cash": "300",
        "card": 0,
        "studyType": "radiografia",
        "doctor": "Carla",
        "date": "Thu Oct 06 2022 18:20:21 GMT-0300 (hora estándar de Argentina)",
        "color": "carmen"
    },
    {
        "id": "_l4lucidgtbn",
        "number": 355,
        "name": "COSTANZO ETHEL",
        "tel": "2914324330",
        "os": "PAMI",
        "study": "CADERAS F, HOMBRO IZQ F, P, COL LS F, P",
        "cash": "500",
        "card": 0,
        "studyType": "radiografia",
        "doctor": "Carla",
        "date": "Thu Oct 06 2022 18:14:36 GMT-0300 (hora estándar de Argentina)",
        "color": "carmen"
    },
    {
        "id": "_o4t6g5p4n9",
        "number": 354,
        "name": "KAMPMEIER CESAR",
        "tel": "2914749519",
        "os": "AVALIAN",
        "study": "TORAX F, P",
        "cash": "300",
        "card": 0,
        "studyType": "radiografia",
        "doctor": "Carla",
        "date": "Thu Oct 06 2022 18:00:43 GMT-0300 (hora estándar de Argentina)",
        "color": "noe"
    },
    {
        "id": "_0bnzprgy6klq",
        "number": 353,
        "name": "CHIUZZI IGNACIO",
        "tel": "2914066254",
        "os": "IOMA",
        "study": "DENTAL, TORAX F",
        "cash": "1600",
        "card": 0,
        "studyType": "radiografia",
        "doctor": "Carla",
        "date": "Thu Oct 06 2022 17:55:00 GMT-0300 (hora estándar de Argentina)",
        "color": "carmen"
    },
    {
        "id": "_woy7zh0mkkl",
        "number": 352,
        "name": "NOEMI NILDA",
        "tel": "2914277124",
        "os": "PAMI",
        "study": "TORAX F",
        "cash": "300",
        "card": 0,
        "studyType": "radiografia",
        "doctor": "Carla",
        "date": "Thu Oct 06 2022 17:51:43 GMT-0300 (hora estándar de Argentina)",
        "color": "noe"
    },
    {
        "id": "_h2eza83usio",
        "number": 351,
        "name": "BARROSO MATIAS",
        "tel": "2915721417",
        "os": "SWISS",
        "study": "DENTAL",
        "cash": 0,
        "card": 0,
        "studyType": "radiografia",
        "doctor": "Carla",
        "date": "Thu Oct 06 2022 17:44:55 GMT-0300 (hora estándar de Argentina)",
        "color": "carmen"
    },
    {
        "id": "_nqlh959f78a",
        "number": 350,
        "name": "BATTAGLIA ENRIQUE",
        "tel": "2914266834",
        "os": "MEDIFE",
        "study": "PIE IZQ F, O",
        "cash": 0,
        "card": 0,
        "studyType": "radiografia",
        "doctor": "Carla",
        "date": "Thu Oct 06 2022 17:40:43 GMT-0300 (hora estándar de Argentina)",
        "color": "noe"
    },
    {
        "id": "_dee32yu2ycn",
        "number": 349,
        "name": "PESCHI NORMA",
        "tel": "2914266894",
        "os": "MEDIFE",
        "study": "ESPINO F, P, TORAX F . COL LS F, P",
        "cash": 0,
        "card": 0,
        "studyType": "radiografia",
        "doctor": "Carla",
        "date": "Thu Oct 06 2022 17:39:34 GMT-0300 (hora estándar de Argentina)",
        "color": "carmen"
    },
    {
        "id": "_y31bq5yg5k",
        "number": 348,
        "name": "COLETTO MARTINA",
        "tel": "2916497282",
        "os": "UTA",
        "study": "DENTAL",
        "cash": 0,
        "card": "300",
        "studyType": "radiografia",
        "doctor": "Carla",
        "date": "Thu Oct 06 2022 17:26:00 GMT-0300 (hora estándar de Argentina)",
        "color": "carmen"
    },
    {
        "id": "_w8n3zfyhyvf",
        "number": 347,
        "name": "ROCCHI LUCIANO",
        "tel": "2914324297",
        "os": "OSDE",
        "study": "TOBILLO IZQ F, P, PIE IZQ F, P, O",
        "cash": 0,
        "card": 0,
        "studyType": "radiografia",
        "doctor": "Carla",
        "date": "Thu Oct 06 2022 17:24:34 GMT-0300 (hora estándar de Argentina)",
        "color": "noe"
    },
    {
        "id": "_c155ntppj2",
        "number": 346,
        "name": "BOLZAN ANTONIO",
        "tel": "2914323880",
        "os": "SWISS",
        "study": "DENTAL",
        "cash": 0,
        "card": 0,
        "studyType": "radiografia",
        "doctor": "Carla",
        "date": "Thu Oct 06 2022 17:22:19 GMT-0300 (hora estándar de Argentina)",
        "color": "carmen"
    },
    {
        "id": "_m9s3ajcvjgn",
        "number": 345,
        "name": "SARDINI ALICIA",
        "tel": "2915754708A",
        "os": "IOMA",
        "study": "DENTAL",
        "cash": "800",
        "card": "800",
        "studyType": "radiografia",
        "doctor": "Carla",
        "date": "Thu Oct 06 2022 17:18:14 GMT-0300 (hora estándar de Argentina)",
        "color": "noe"
    },
    {
        "id": "_nnlyijxvep",
        "number": 344,
        "name": "GOMEZ PEDRO",
        "tel": "2914297107",
        "os": "PART",
        "study": "TOBILLO D F, P",
        "cash": "1700",
        "card": 0,
        "studyType": "radiografia",
        "doctor": "Carla",
        "date": "Thu Oct 06 2022 17:14:46 GMT-0300 (hora estándar de Argentina)",
        "color": "carmen"
    },
    {
        "id": "_mnjs46pg7v",
        "number": 343,
        "name": "IZCO LUCIANO",
        "tel": "2914326119",
        "os": "AVALIAN",
        "study": "RODILLA IZQ F, P",
        "cash": "300",
        "card": 0,
        "studyType": "radiografia",
        "doctor": "Carla",
        "date": "Thu Oct 06 2022 17:12:16 GMT-0300 (hora estándar de Argentina)",
        "color": "noe"
    },
    {
        "id": "_ty52ddxn1j",
        "number": 342,
        "name": "ALONSO MAIRA",
        "tel": "2916432462",
        "os": "MEDIFE",
        "study": "PIES CON APOYO F, P, P EST",
        "cash": 0,
        "card": 0,
        "studyType": "radiografia",
        "doctor": "Carla",
        "date": "Thu Oct 06 2022 17:11:06 GMT-0300 (hora estándar de Argentina)",
        "color": "carmen"
    },
    {
        "id": "_3oxgft64gt4",
        "number": 341,
        "name": "LEON CRISTIAN",
        "tel": "2914231303",
        "os": "IOMA",
        "study": "DENTAL",
        "cash": "800",
        "card": 0,
        "studyType": "radiografia",
        "doctor": "Carla",
        "date": "Thu Oct 06 2022 17:07:45 GMT-0300 (hora estándar de Argentina)",
        "color": "carmen"
    },
    {
        "id": "_drzdzmqwvxm",
        "number": 340,
        "name": "FORSTER ALEJANDRA",
        "tel": "2914049992",
        "os": "PART",
        "study": "DENTAL",
        "cash": "2300",
        "card": 0,
        "studyType": "radiografia",
        "doctor": "Carla",
        "date": "Thu Oct 06 2022 17:00:00 GMT-0300 (hora estándar de Argentina)",
        "color": "carmen"
    },
    {
        "id": "_1f2ipuysmr9",
        "number": 339,
        "name": "BUSTOS IMANOL",
        "tel": "2915752258",
        "os": "UNS",
        "study": "DENTAL",
        "cash": 0,
        "card": 0,
        "studyType": "radiografia",
        "doctor": "Carla",
        "date": "Thu Oct 06 2022 16:59:26 GMT-0300 (hora estándar de Argentina)",
        "color": "noe"
    },
    {
        "id": "_c3btoed9h8",
        "number": 338,
        "name": "bohn vanesa",
        "tel": "2914278523",
        "os": "uns",
        "study": "dental",
        "cash": "2300",
        "card": 0,
        "studyType": "radiografia",
        "doctor": "Carla",
        "date": "Thu Oct 06 2022 16:53:43 GMT-0300 (hora estándar de Argentina)",
        "color": "noe"
    },
    {
        "id": "_ujv7s3e56cs",
        "number": 337,
        "name": "MONTASTRUC DENISE",
        "tel": "2914819950",
        "os": "IOMA",
        "study": "RODILLAS F, P",
        "cash": "1200",
        "card": 0,
        "studyType": "radiografia",
        "doctor": "Carla",
        "date": "Thu Oct 06 2022 16:42:14 GMT-0300 (hora estándar de Argentina)",
        "color": "noe"
    },
    {
        "id": "_vdg20ojaa1e",
        "number": 336,
        "name": "MARTINEZ MARIO",
        "tel": "2921434615",
        "os": "UOM",
        "study": "TORAX F",
        "cash": 0,
        "card": 0,
        "studyType": "radiografia",
        "doctor": "Carla",
        "date": "Thu Oct 06 2022 16:34:20 GMT-0300 (hora estándar de Argentina)",
        "color": "noe"
    },
    {
        "id": "_hhld4hvhyxq",
        "number": 335,
        "name": "BERNARDI FLAVIA",
        "tel": "2914020386",
        "os": "IOMA",
        "study": "PIES F, P, TOBILLOS F, P",
        "cash": "2000",
        "card": 0,
        "studyType": "radiografia",
        "doctor": "Carla",
        "date": "Thu Oct 06 2022 16:21:22 GMT-0300 (hora estándar de Argentina)",
        "color": "carmen"
    },
    {
        "id": "_bb2trvgrcc",
        "number": 334,
        "name": "NOVOA NATALIA",
        "tel": "2915724770",
        "os": "UOM",
        "study": "DENTAL",
        "cash": 0,
        "card": 0,
        "studyType": "radiografia",
        "doctor": "Carla",
        "date": "Thu Oct 06 2022 16:14:17 GMT-0300 (hora estándar de Argentina)",
        "color": "carmen"
    },
    {
        "id": "_9l1zmr7u3ke",
        "number": 333,
        "name": "MACCHI JOAQUIN",
        "tel": "2914440202",
        "os": "UOMA",
        "study": "MUSLO D F, P",
        "cash": 0,
        "card": 0,
        "studyType": "radiografia",
        "doctor": "Carla",
        "date": "Thu Oct 06 2022 16:03:29 GMT-0300 (hora estándar de Argentina)",
        "color": "noe"
    },
    {
        "id": "_051r1m02c0bl",
        "number": 332,
        "name": "VIGNATTI ANTONELLA ",
        "tel": "2914198424",
        "os": "SWISS",
        "study": "TORAX F",
        "cash": 0,
        "card": 0,
        "studyType": "radiografia",
        "doctor": "Leonardo",
        "date": "Thu Oct 06 2022 15:45:43 GMT-0300 (hora estándar de Argentina)",
        "color": "noe"
    },
    {
        "id": "_anrwalyvfh",
        "number": 331,
        "name": "CUADRADO PAULA",
        "tel": "2916491573",
        "os": "IOMA",
        "study": "TORAX F",
        "cash": "800",
        "card": 0,
        "studyType": "radiografia",
        "doctor": "Leonardo",
        "date": "Thu Oct 06 2022 15:39:58 GMT-0300 (hora estándar de Argentina)",
        "color": "carmen"
    },
    {
        "id": "_gc1d8nxevli",
        "number": 330,
        "name": "STREMEL LAUTARO",
        "tel": "2914324149",
        "os": "UTA",
        "study": "MMI, ESPINO F, P",
        "cash": "500",
        "card": 0,
        "studyType": "radiografia",
        "doctor": "Leonardo",
        "date": "Thu Oct 06 2022 15:35:03 GMT-0300 (hora estándar de Argentina)",
        "color": "carmen"
    },
    {
        "id": "_ayrfwtartdk",
        "number": 329,
        "name": "FERNANDEZ ANALIA",
        "tel": "2914220833",
        "os": "IOMA",
        "study": "HOMBRO, IZQ F, AXIAL ESC",
        "cash": 0,
        "card": "1200",
        "studyType": "radiografia",
        "doctor": "Leonardo",
        "date": "Thu Oct 06 2022 15:32:22 GMT-0300 (hora estándar de Argentina)",
        "color": "carmen"
    },
    {
        "id": "_oebrucp8e8",
        "number": 328,
        "name": "ANDREUCETTI NOEMI",
        "tel": "2914258494",
        "os": "UNS",
        "study": "ARBOL URINARIO",
        "cash": "300",
        "card": 0,
        "studyType": "radiografia",
        "doctor": "Leonardo",
        "date": "Thu Oct 06 2022 15:28:17 GMT-0300 (hora estándar de Argentina)",
        "color": "carmen"
    },
    {
        "id": "_otzrpebzxs",
        "number": 327,
        "name": "VALLASCIANI FLORENCIA",
        "tel": "2915279305",
        "os": "PART",
        "study": "TORAX F",
        "cash": "1700",
        "card": 0,
        "studyType": "radiografia",
        "doctor": "Leonardo",
        "date": "Thu Oct 06 2022 15:17:44 GMT-0300 (hora estándar de Argentina)",
        "color": "carmen"
    },
    {
        "id": "_5yllo055ur",
        "number": 326,
        "name": "MARTINEZ NAHUEL",
        "tel": "29156945686",
        "os": "MEDIFE",
        "study": "TORAX F",
        "cash": 0,
        "card": 0,
        "studyType": "radiografia",
        "doctor": "Leonardo",
        "date": "Thu Oct 06 2022 15:16:07 GMT-0300 (hora estándar de Argentina)",
        "color": "carmen"
    },
    {
        "id": "_n13yrnprpt",
        "number": 325,
        "name": "CASTRO ARES DANIEL",
        "tel": "2915204090",
        "os": "FEDERADA",
        "study": "DENTAL",
        "cash": "300",
        "card": 0,
        "studyType": "radiografia",
        "doctor": "Leonardo",
        "date": "Thu Oct 06 2022 14:57:18 GMT-0300 (hora estándar de Argentina)",
        "color": "carmen"
    },
    {
        "id": "_p5jdypx0t49",
        "number": 324,
        "name": "DOMINELLA GRACIELA",
        "tel": "2914664140",
        "os": "IOMA",
        "study": "DENTAL",
        "cash": "800",
        "card": 0,
        "studyType": "radiografia",
        "doctor": "Leonardo",
        "date": "Thu Oct 06 2022 14:44:43 GMT-0300 (hora estándar de Argentina)",
        "color": "carmen"
    },
    {
        "id": "_eno98u4ci1s",
        "number": 323,
        "name": "ZACARIAZ LEONARDO",
        "tel": "2914360849",
        "os": "PART",
        "study": "DENTAL",
        "cash": "2300",
        "card": 0,
        "studyType": "radiografia",
        "doctor": "Leonardo",
        "date": "Thu Oct 06 2022 14:43:20 GMT-0300 (hora estándar de Argentina)",
        "color": "carmen"
    },
    {
        "id": "_2o3c9efule5",
        "number": 322,
        "name": "MARTINEZ NIVIA",
        "tel": "2914672536",
        "os": "PART",
        "study": "TORAX F",
        "cash": "1700",
        "card": 0,
        "studyType": "radiografia",
        "doctor": "Leonardo",
        "date": "Thu Oct 06 2022 14:31:54 GMT-0300 (hora estándar de Argentina)",
        "color": "carmen"
    },
    {
        "id": "_6fj4k8luhm",
        "number": 321,
        "name": "BASTARD JUANA",
        "tel": "2923427144",
        "os": "OSDE",
        "study": "DENTAL",
        "cash": 0,
        "card": 0,
        "studyType": "radiografia",
        "doctor": "Leonardo",
        "date": "Thu Oct 06 2022 14:30:38 GMT-0300 (hora estándar de Argentina)",
        "color": "carmen"
    },
    {
        "id": "_lmoxslzk5rr",
        "number": 320,
        "name": "OLIVERO MIRTA",
        "tel": "2923439193",
        "os": "IOMA",
        "study": "DENTAL",
        "cash": "800",
        "card": 0,
        "studyType": "radiografia",
        "doctor": "Leonardo",
        "date": "Thu Oct 06 2022 14:26:42 GMT-0300 (hora estándar de Argentina)",
        "color": "carmen"
    },
    {
        "id": "_wqd45iufecs",
        "number": 319,
        "name": "VILLALBA SUSANA",
        "tel": "2932506129",
        "os": "IOMA",
        "study": "DENTAL",
        "cash": "800",
        "card": 0,
        "studyType": "radiografia",
        "doctor": "Leonardo",
        "date": "Thu Oct 06 2022 14:24:18 GMT-0300 (hora estándar de Argentina)",
        "color": "carmen"
    },
    {
        "id": "_05ytdsk8vavh",
        "number": 318,
        "name": "ARMATA LUDMILA",
        "tel": "2916494106",
        "os": "OSPECON",
        "study": "DENTAL",
        "cash": "300",
        "card": 0,
        "studyType": "radiografia",
        "doctor": "Leonardo",
        "date": "Thu Oct 06 2022 14:21:54 GMT-0300 (hora estándar de Argentina)",
        "color": "carmen"
    },
    {
        "id": "_4xh6rjodkpp",
        "number": 258,
        "name": "LOPEZ VIVIANA",
        "tel": "54 9 3512 14-1515",
        "os": "IOMA",
        "study": "TIROIDES",
        "cash": "2000",
        "card": 0,
        "studyType": "ecografia",
        "doctor": "Leonardo",
        "date": "Thu Oct 06 2022 14:05:22 GMT-0300 (hora estándar de Argentina)"
    },
    {
        "id": "_9xwmss4wbnq",
        "number": 317,
        "name": "HEILAND DANA",
        "tel": "2916460288",
        "os": "OATRONES",
        "study": "DENTAL",
        "cash": "2300",
        "card": 0,
        "studyType": "radiografia",
        "doctor": "Leonardo",
        "date": "Thu Oct 06 2022 13:50:16 GMT-0300 (hora estándar de Argentina)",
        "color": "carmen"
    },
    {
        "id": "_oc8db309ra",
        "number": 316,
        "name": "WIRSCKE DANIEL",
        "tel": "2914054990",
        "os": "SWISS",
        "study": "MANOS MUÑECAS F, P",
        "cash": 0,
        "card": 0,
        "studyType": "radiografia",
        "doctor": "Leonardo",
        "date": "Thu Oct 06 2022 13:44:35 GMT-0300 (hora estándar de Argentina)",
        "color": "carmen"
    },
    {
        "id": "_htfiqtd421r",
        "number": 257,
        "name": "VAZQUEZ ADRIANA",
        "tel": "2914144232",
        "os": "IOMA",
        "study": "DOP V C, ABD, URIN",
        "cash": 0,
        "card": "7800",
        "studyType": "ecografia",
        "doctor": "Leonardo",
        "date": "Thu Oct 06 2022 13:39:26 GMT-0300 (hora estándar de Argentina)"
    },
    {
        "id": "_4zn5w2ujwpv",
        "number": 315,
        "name": "LORES CHIESA AGOSTINA",
        "tel": "2915269426",
        "os": "IOMA",
        "study": "RODILLA D F, P",
        "cash": "800",
        "card": 0,
        "studyType": "radiografia",
        "doctor": "Leonardo",
        "date": "Thu Oct 06 2022 13:25:47 GMT-0300 (hora estándar de Argentina)",
        "color": "carmen"
    },
    {
        "id": "_iaa8a78jn9g",
        "number": 314,
        "name": "ZARATE CAROLINA",
        "tel": "2914127467",
        "os": "OSPBB",
        "study": "TORAX F, P, SPN, FNP",
        "cash": "300",
        "card": 0,
        "studyType": "radiografia",
        "doctor": "Leonardo",
        "date": "Thu Oct 06 2022 13:19:41 GMT-0300 (hora estándar de Argentina)",
        "color": "carmen"
    },
    {
        "id": "_ibgcvyrnho",
        "number": 313,
        "name": "LA FICCO GUZZO GENOVEVA",
        "tel": "2914425518",
        "os": "MEDIFE",
        "study": "DENTAL",
        "cash": 0,
        "card": 0,
        "studyType": "radiografia",
        "doctor": "Leonardo",
        "date": "Thu Oct 06 2022 13:18:10 GMT-0300 (hora estándar de Argentina)",
        "color": "carmen"
    },
    {
        "id": "_pd0hbe0f1y",
        "number": 256,
        "name": "matta sofia",
        "tel": "11111",
        "os": "IOMA",
        "study": "ABD",
        "cash": "2000",
        "card": 0,
        "studyType": "ecografia",
        "doctor": "Leonardo",
        "date": "Thu Oct 06 2022 13:11:13 GMT-0300 (hora estándar de Argentina)"
    },
    {
        "id": "_90xqdfemaj",
        "number": 312,
        "name": "MARCOS GUILLERMO",
        "tel": "2932636388",
        "os": "CASA",
        "study": "DENTAL",
        "cash": 0,
        "card": 0,
        "studyType": "radiografia",
        "doctor": "Leonardo",
        "date": "Thu Oct 06 2022 13:01:36 GMT-0300 (hora estándar de Argentina)",
        "color": "carmen"
    },
    {
        "id": "_nedhn7be4ol",
        "number": 311,
        "name": "SIMON CECILIA",
        "tel": "2914363229",
        "os": "UNS",
        "study": "DENTAL",
        "cash": "2300",
        "card": 0,
        "studyType": "radiografia",
        "doctor": "Leonardo",
        "date": "Thu Oct 06 2022 12:57:34 GMT-0300 (hora estándar de Argentina)",
        "color": "dami"
    },
    {
        "id": "_4pvr2t5lx8",
        "number": 310,
        "name": "MACRI NORMA",
        "tel": "2914755972",
        "os": "LUZ Y F",
        "study": "TORAX F",
        "cash": "1700",
        "card": 0,
        "studyType": "radiografia",
        "doctor": "Leonardo",
        "date": "Thu Oct 06 2022 12:54:44 GMT-0300 (hora estándar de Argentina)",
        "color": "noe"
    },
    {
        "id": "_mmn34y2tukn",
        "number": 309,
        "name": "VITALE SANDRA",
        "tel": "2914138497",
        "os": "FARMACIA",
        "study": "DENTAL",
        "cash": "300",
        "card": 0,
        "studyType": "radiografia",
        "doctor": "Leonardo",
        "date": "Thu Oct 06 2022 12:46:46 GMT-0300 (hora estándar de Argentina)",
        "color": "dami"
    },
    {
        "id": "_3aw4179mltz",
        "number": 308,
        "name": "MONTENEGRO BRUNO",
        "tel": "2915027838",
        "os": "GALENO",
        "study": "COL LUMB F, P, TORAX F, P",
        "cash": "300",
        "card": 0,
        "studyType": "radiografia",
        "doctor": "Leonardo",
        "date": "Thu Oct 06 2022 12:42:57 GMT-0300 (hora estándar de Argentina)",
        "color": "noe"
    },
    {
        "id": "_9rv6co935p",
        "number": 307,
        "name": "ROMERO JUANA",
        "tel": "2914181742",
        "os": "PAMI",
        "study": "CADERAS F, P, COL LS F, P",
        "cash": "500",
        "card": 0,
        "studyType": "radiografia",
        "doctor": "Leonardo",
        "date": "Thu Oct 06 2022 12:40:37 GMT-0300 (hora estándar de Argentina)",
        "color": "dami"
    },
    {
        "id": "_tv0gpdx2ll8",
        "number": 306,
        "name": "CORONEL JONATHAN",
        "tel": "2923693560",
        "os": "PART",
        "study": "DENTAL",
        "cash": 0,
        "card": "2300",
        "studyType": "radiografia",
        "doctor": "Leonardo",
        "date": "Thu Oct 06 2022 12:27:57 GMT-0300 (hora estándar de Argentina)",
        "color": "dami"
    },
    {
        "id": "_dsfr02zku9c",
        "number": 305,
        "name": "COFRE SANDRO",
        "tel": "2915121108",
        "os": "PART",
        "study": "TORAX F",
        "cash": "1700",
        "card": 0,
        "studyType": "radiografia",
        "doctor": "Leonardo",
        "date": "Thu Oct 06 2022 12:27:08 GMT-0300 (hora estándar de Argentina)",
        "color": "noe"
    },
    {
        "id": "_lttjvyv5ahl",
        "number": 304,
        "name": "JUNCIEL GABRIELA",
        "tel": "2915068893",
        "os": "UNS",
        "study": "DENTAL",
        "cash": "2300",
        "card": 0,
        "studyType": "radiografia",
        "doctor": "Leonardo",
        "date": "Thu Oct 06 2022 12:22:50 GMT-0300 (hora estándar de Argentina)",
        "color": "dami"
    },
    {
        "id": "_dpkubpjft4o",
        "number": 303,
        "name": "CARRARI UMA",
        "tel": "2914736202",
        "os": "PART",
        "study": "MNP FNP CAVUN",
        "cash": "3500",
        "card": 0,
        "studyType": "radiografia",
        "doctor": "Leonardo",
        "date": "Thu Oct 06 2022 12:10:55 GMT-0300 (hora estándar de Argentina)",
        "color": "noe"
    },
    {
        "id": "_w5b2hbjwxu",
        "number": 302,
        "name": "FLORES AGUSTINA",
        "tel": "2914232499",
        "os": "MEDIFE",
        "study": "TORAX F",
        "cash": 0,
        "card": 0,
        "studyType": "radiografia",
        "doctor": "Leonardo",
        "date": "Thu Oct 06 2022 12:08:26 GMT-0300 (hora estándar de Argentina)",
        "color": "noe"
    },
    {
        "id": "_fzw1opu3r8o",
        "number": 301,
        "name": "OVELAR MARTIN",
        "tel": "2915038897",
        "os": "PART",
        "study": "MNP FNP",
        "cash": "3000",
        "card": 0,
        "studyType": "radiografia",
        "doctor": "Leonardo",
        "date": "Thu Oct 06 2022 12:06:05 GMT-0300 (hora estándar de Argentina)",
        "color": "dami"
    },
    {
        "id": "_hwzzlbbbrle",
        "number": 300,
        "name": "CORONEL SUSANA",
        "tel": "2915043868",
        "os": "IOMA",
        "study": "HUMERO FYP CODO FYP",
        "cash": "1000",
        "card": 0,
        "studyType": "radiografia",
        "doctor": "Leonardo",
        "date": "Thu Oct 06 2022 12:04:29 GMT-0300 (hora estándar de Argentina)",
        "color": "noe"
    },
    {
        "id": "_her44zwezoq",
        "number": 299,
        "name": "BISCAICHIPY BEATRIZ",
        "tel": "2923457222",
        "os": "AVALIAN",
        "study": "DENTAL",
        "cash": "300",
        "card": 0,
        "studyType": "radiografia",
        "doctor": "Leonardo",
        "date": "Thu Oct 06 2022 11:49:44 GMT-0300 (hora estándar de Argentina)",
        "color": "dami"
    },
    {
        "id": "_kqeojn8my8",
        "number": 298,
        "name": "AMOROSI EDUARDO",
        "tel": "2914147308",
        "os": "FEDERADA",
        "study": "DEDO FYP",
        "cash": "300",
        "card": 0,
        "studyType": "radiografia",
        "doctor": "Leonardo",
        "date": "Thu Oct 06 2022 11:48:17 GMT-0300 (hora estándar de Argentina)",
        "color": "noe"
    },
    {
        "id": "_mmtm8d3vppq",
        "number": 297,
        "name": "MACAZAGA GABRIELA",
        "tel": "2914626504",
        "os": "DOSEM",
        "study": "PIES FYP",
        "cash": "300",
        "card": 0,
        "studyType": "radiografia",
        "doctor": "Leonardo",
        "date": "Thu Oct 06 2022 11:46:09 GMT-0300 (hora estándar de Argentina)",
        "color": "noe"
    },
    {
        "id": "_g32gf4581mf",
        "number": 296,
        "name": "\tDENIN FRANCO",
        "tel": "2915012572",
        "os": "PART",
        "study": "TORAX F",
        "cash": "1700",
        "card": 0,
        "studyType": "radiografia",
        "doctor": "Leonardo",
        "date": "Thu Oct 06 2022 11:43:52 GMT-0300 (hora estándar de Argentina)",
        "color": "dami"
    },
    {
        "id": "_75sy1hiin5i",
        "number": 254,
        "name": "DURAN MARCELO",
        "tel": "2914764900",
        "os": "PART",
        "study": "DOPPLER ARTERIA VENOSO MMI",
        "cash": "7500",
        "card": 0,
        "studyType": "ecografia",
        "doctor": "Leonardo",
        "date": "Thu Oct 06 2022 11:42:03 GMT-0300 (hora estándar de Argentina)"
    },
    {
        "id": "_qj5tvvzjc6l",
        "number": 295,
        "name": "SCHWERDT MIRIAN",
        "tel": "2914765900",
        "os": "IOMA",
        "study": "HOMBROS F PELVIS",
        "cash": "1000",
        "card": 0,
        "studyType": "radiografia",
        "doctor": "Leonardo",
        "date": "Thu Oct 06 2022 11:40:17 GMT-0300 (hora estándar de Argentina)",
        "color": "dami"
    },
    {
        "id": "_5wf2kpsbopc",
        "number": 294,
        "name": "VAZQUEZ ANA BEATRIZ",
        "tel": "2914418248",
        "os": "OSDE",
        "study": "MNP",
        "cash": 0,
        "card": 0,
        "studyType": "radiografia",
        "doctor": "Leonardo",
        "date": "Thu Oct 06 2022 11:39:24 GMT-0300 (hora estándar de Argentina)",
        "color": "noe"
    },
    {
        "id": "_a4earb8d354",
        "number": 293,
        "name": "PANDOLFI MATEO",
        "tel": "2914774500",
        "os": "SWISS",
        "study": "MUÑECA FYP",
        "cash": 0,
        "card": 0,
        "studyType": "radiografia",
        "doctor": "Leonardo",
        "date": "Thu Oct 06 2022 11:29:08 GMT-0300 (hora estándar de Argentina)",
        "color": "noe"
    },
    {
        "id": "_8a9inv7s8lj",
        "number": 253,
        "name": "ORIOLI",
        "tel": "2914700768",
        "os": "IOMA",
        "study": "ABD",
        "cash": "0",
        "card": "2000",
        "studyType": "ecografia",
        "doctor": "Leonardo",
        "date": "Thu Oct 06 2022 11:25:43 GMT-0300 (hora estándar de Argentina)"
    },
    {
        "id": "_i7npsx14z8l",
        "number": 292,
        "name": "MUZI DIEGO",
        "tel": "2915039641",
        "os": "IOMA",
        "study": "MNP",
        "cash": "800",
        "card": 0,
        "studyType": "radiografia",
        "doctor": "Leonardo",
        "date": "Thu Oct 06 2022 11:24:16 GMT-0300 (hora estándar de Argentina)",
        "color": "noe"
    },
    {
        "id": "_3umhkc0qykx",
        "number": 291,
        "name": "\tFENIZI GERMAN PABLO",
        "tel": "2914736956",
        "os": "OSDE",
        "study": "DENTAL",
        "cash": 0,
        "card": 0,
        "studyType": "radiografia",
        "doctor": "Leonardo",
        "date": "Thu Oct 06 2022 11:23:00 GMT-0300 (hora estándar de Argentina)",
        "color": "dami"
    },
    {
        "id": "_io524iya6z",
        "number": 290,
        "name": "PALAVECINO HORACIO",
        "tel": "\t2914417509",
        "os": "IOMA",
        "study": "DENTAL",
        "cash": "800",
        "card": 0,
        "studyType": "radiografia",
        "doctor": "Leonardo",
        "date": "Thu Oct 06 2022 11:18:43 GMT-0300 (hora estándar de Argentina)",
        "color": "dami"
    },
    {
        "id": "_38x4q8zymm4",
        "number": 289,
        "name": "MACERATESI MONICA",
        "tel": "2914417509",
        "os": "IOMA",
        "study": "DENTAL",
        "cash": "800",
        "card": 0,
        "studyType": "radiografia",
        "doctor": "Leonardo",
        "date": "Thu Oct 06 2022 11:18:12 GMT-0300 (hora estándar de Argentina)",
        "color": "dami"
    },
    {
        "id": "_piy5fa74dw",
        "number": 252,
        "name": "RODRIGUEZ OSVALDO",
        "tel": "2916074530",
        "os": "FEDERADA",
        "study": "ABD",
        "cash": 0,
        "card": 0,
        "studyType": "ecografia",
        "doctor": "Leonardo",
        "date": "Thu Oct 06 2022 11:06:04 GMT-0300 (hora estándar de Argentina)"
    },
    {
        "id": "_ghbcrfji5",
        "number": 251,
        "name": "\tBECCARIA GUSTAVO DAVID",
        "tel": "2914741792",
        "os": "OSDE",
        "study": "ABD",
        "cash": 0,
        "card": 0,
        "studyType": "ecografia",
        "doctor": "Leonardo",
        "date": "Thu Oct 06 2022 11:04:15 GMT-0300 (hora estándar de Argentina)"
    },
    {
        "id": "_rj4iy08ql08",
        "number": 288,
        "name": "ORIFICI MARIANELA",
        "tel": "2914448395",
        "os": "IOMA",
        "study": "DENTAL",
        "cash": "800",
        "card": 0,
        "studyType": "radiografia",
        "doctor": "Leonardo",
        "date": "Thu Oct 06 2022 10:54:26 GMT-0300 (hora estándar de Argentina)",
        "color": "dami"
    },
    {
        "id": "_cgupl7xrc1i",
        "number": 250,
        "name": "CABRERA GISELLA",
        "tel": "2914403164",
        "os": "PART",
        "study": "EMBARAZO",
        "cash": "3000",
        "card": 0,
        "studyType": "ecografia",
        "doctor": "Leonardo",
        "date": "Thu Oct 06 2022 10:53:20 GMT-0300 (hora estándar de Argentina)"
    },
    {
        "id": "_wmtguve2qe",
        "number": 287,
        "name": "HAAG GASTON",
        "tel": "2914412719",
        "os": "PART",
        "study": "TOBILLO FYP",
        "cash": "1700",
        "card": 0,
        "studyType": "radiografia",
        "doctor": "Carla",
        "date": "Thu Oct 06 2022 10:52:11 GMT-0300 (hora estándar de Argentina)",
        "color": "dami"
    },
    {
        "id": "_c65lx6g8hih",
        "number": 286,
        "name": "VARELA MIRTA",
        "tel": "2914186332",
        "os": "UNS",
        "study": "MUÑECA FYP",
        "cash": 0,
        "card": 0,
        "studyType": "radiografia",
        "doctor": "Carla",
        "date": "Thu Oct 06 2022 10:51:01 GMT-0300 (hora estándar de Argentina)",
        "color": "dami"
    },
    {
        "id": "_ckgu87n5pnc",
        "number": 285,
        "name": "MOLINA ANA LUZ",
        "tel": "2914042258",
        "os": "IOMA",
        "study": "DENTAL",
        "cash": "800",
        "card": 0,
        "studyType": "radiografia",
        "doctor": "Carla",
        "date": "Thu Oct 06 2022 10:48:43 GMT-0300 (hora estándar de Argentina)",
        "color": "dami"
    },
    {
        "id": "_pt31gu19lks",
        "number": 284,
        "name": "PEREZ DIEGO",
        "tel": "2916486846",
        "os": "OSTEL",
        "study": "MNP FNP",
        "cash": "300",
        "card": 0,
        "studyType": "radiografia",
        "doctor": "Carla",
        "date": "Thu Oct 06 2022 10:41:06 GMT-0300 (hora estándar de Argentina)",
        "color": "dami"
    },
    {
        "id": "_00tspbl08k7s",
        "number": 283,
        "name": "SENESTRO ELINA",
        "tel": "2916485073",
        "os": "FEDERADA",
        "study": "RODILLA F P AXIAL",
        "cash": "300",
        "card": 0,
        "studyType": "radiografia",
        "doctor": "Carla",
        "date": "Thu Oct 06 2022 10:32:56 GMT-0300 (hora estándar de Argentina)",
        "color": "dami"
    },
    {
        "id": "_mrycprvrd2o",
        "number": 282,
        "name": "ESPINOZA ROBERTO",
        "tel": "2916462664",
        "os": "PART",
        "study": "DENTAL",
        "cash": 0,
        "card": "2300",
        "studyType": "radiografia",
        "doctor": "Carla",
        "date": "Thu Oct 06 2022 10:16:16 GMT-0300 (hora estándar de Argentina)",
        "color": "dami"
    },
    {
        "id": "_vvanb1em2og",
        "number": 249,
        "name": "ARCEO MARCELA",
        "tel": "2914469699",
        "os": "IOMA",
        "study": "DOPPLES VASOS DE CUELLO",
        "cash": "4500",
        "card": 0,
        "studyType": "ecografia",
        "doctor": "Leonardo",
        "date": "Thu Oct 06 2022 10:08:14 GMT-0300 (hora estándar de Argentina)"
    },
    {
        "id": "_1aceeu2vz93i",
        "number": 248,
        "name": "CIARROCCHI JORGE",
        "tel": "2915044801",
        "os": "UNS",
        "study": "PARTES BLANDAS",
        "cash": 0,
        "card": 0,
        "studyType": "ecografia",
        "doctor": "Leonardo",
        "date": "Thu Oct 06 2022 10:05:25 GMT-0300 (hora estándar de Argentina)"
    },
    {
        "id": "_vnbvju67ze",
        "number": 281,
        "name": "GAITAN VIVIANA",
        "tel": "2914631490",
        "os": "OSDE",
        "study": "CERVICAL LUMBAR FYP",
        "cash": 0,
        "card": 0,
        "studyType": "radiografia",
        "doctor": "Carla",
        "date": "Thu Oct 06 2022 10:04:28 GMT-0300 (hora estándar de Argentina)",
        "color": "dami"
    },
    {
        "id": "_9jn4cgx97g",
        "number": 280,
        "name": "ARES LUCIANA ANDREA",
        "tel": "2914410702",
        "os": "OSDE",
        "study": "TORAX FYP",
        "cash": 0,
        "card": 0,
        "studyType": "radiografia",
        "doctor": "Carla",
        "date": "Thu Oct 06 2022 10:01:06 GMT-0300 (hora estándar de Argentina)",
        "color": "noe"
    },
    {
        "id": "_38dr4pqpt9c",
        "number": 279,
        "name": "IRIBARREN CLAUDIA",
        "tel": "2916449687",
        "os": "UNS",
        "study": "DENTAL",
        "cash": 0,
        "card": 0,
        "studyType": "radiografia",
        "doctor": "Carla",
        "date": "Thu Oct 06 2022 09:55:40 GMT-0300 (hora estándar de Argentina)",
        "color": "dami"
    },
    {
        "id": "_tqsy2x8waoe",
        "number": 278,
        "name": "GRAZIANI ELSA BEATRIZ",
        "tel": "2914540750",
        "os": "PAMI",
        "study": "ESPINO FYP MMI",
        "cash": "300",
        "card": 0,
        "studyType": "radiografia",
        "doctor": "Carla",
        "date": "Thu Oct 06 2022 09:53:54 GMT-0300 (hora estándar de Argentina)",
        "color": "dami"
    },
    {
        "id": "_d5gpjl8pjea",
        "number": 247,
        "name": "VIVAS ANDREA",
        "tel": "2914442779",
        "os": "IOMA",
        "study": "RODILLA",
        "cash": "2000",
        "card": 0,
        "studyType": "ecografia",
        "doctor": "Leonardo",
        "date": "Thu Oct 06 2022 09:39:41 GMT-0300 (hora estándar de Argentina)"
    },
    {
        "id": "_gn7ow2d43zq",
        "number": 276,
        "name": "GONZALEZ LAURA",
        "tel": "291690749",
        "os": "SANIDAD",
        "study": "DENTAL",
        "cash": 0,
        "card": 0,
        "studyType": "radiografia",
        "doctor": "Carla",
        "date": "Thu Oct 06 2022 09:37:05 GMT-0300 (hora estándar de Argentina)",
        "color": "noe"
    },
    {
        "id": "_uk47qojbdfk",
        "number": 275,
        "name": "GUERELLO MARIA",
        "tel": "2914134650",
        "os": "FEDERADA",
        "study": "MANO FYP DENTAL  TOMO AMBOS MAX",
        "cash": 0,
        "card": "6900",
        "studyType": "radiografia",
        "doctor": "Carla",
        "date": "Thu Oct 06 2022 09:25:09 GMT-0300 (hora estándar de Argentina)",
        "color": "dami"
    },
    {
        "id": "_uehlj87zy4",
        "number": 274,
        "name": "BARES CINTHYA",
        "tel": "2914184201",
        "os": "UNS",
        "study": "ESPINOGRAFIA FYP",
        "cash": 0,
        "card": 0,
        "studyType": "radiografia",
        "doctor": "Carla",
        "date": "Thu Oct 06 2022 09:19:37 GMT-0300 (hora estándar de Argentina)",
        "color": "dami"
    },
    {
        "id": "_3ysrqufvof2",
        "number": 273,
        "name": "GUILLERMO MARIA",
        "tel": "2914710784",
        "os": "IOMA",
        "study": "DENTAL",
        "cash": "800",
        "card": 0,
        "studyType": "radiografia",
        "doctor": "Carla",
        "date": "Thu Oct 06 2022 09:14:03 GMT-0300 (hora estándar de Argentina)",
        "color": "dami"
    },
    {
        "id": "_atcczh62y3u",
        "number": 246,
        "name": "PERELLI HERNAN",
        "tel": "2916436692",
        "os": "PART",
        "study": "RODILLA",
        "cash": "3000",
        "card": 0,
        "studyType": "ecografia",
        "doctor": "Leonardo",
        "date": "Thu Oct 06 2022 09:13:04 GMT-0300 (hora estándar de Argentina)"
    },
    {
        "id": "_z2p0h5152xa",
        "number": 245,
        "name": "OLEA PABLO",
        "tel": "2914168225",
        "os": "LYF",
        "study": "ABD",
        "cash": 0,
        "card": 0,
        "studyType": "ecografia",
        "doctor": "Leonardo",
        "date": "Thu Oct 06 2022 09:12:14 GMT-0300 (hora estándar de Argentina)"
    },
    {
        "id": "_mkvrlumgo9e",
        "number": 272,
        "name": "ROLDAN MIRTA",
        "tel": "2916487900",
        "os": "PART",
        "study": "DENTAL",
        "cash": "2300",
        "card": 0,
        "studyType": "radiografia",
        "doctor": "Carla",
        "date": "Thu Oct 06 2022 09:02:57 GMT-0300 (hora estándar de Argentina)",
        "color": "dami"
    },
    {
        "id": "_vb5z1gij3t",
        "number": 271,
        "name": "PULIAFITO CONCEPCION",
        "tel": "2932637290",
        "os": "IOMA ",
        "study": "PIE FYP LUMBAR FYP CADERA DER FYP",
        "cash": "2000",
        "card": 0,
        "studyType": "radiografia",
        "doctor": "Carla",
        "date": "Thu Oct 06 2022 09:02:05 GMT-0300 (hora estándar de Argentina)",
        "color": "dami"
    },
    {
        "id": "_h3uk13tiwqi",
        "number": 270,
        "name": "CATALI FERNANDO",
        "tel": "2938542046",
        "os": "IOMA",
        "study": "DENTAL",
        "cash": "800",
        "card": 0,
        "studyType": "radiografia",
        "doctor": "Carla",
        "date": "Thu Oct 06 2022 08:46:39 GMT-0300 (hora estándar de Argentina)",
        "color": "dami"
    },
    {
        "id": "_ztse0iga64l",
        "number": 269,
        "name": "LOPEZ CAROLINA",
        "tel": "2914043719",
        "os": "IOMA",
        "study": "DENTAL",
        "cash": "800",
        "card": 0,
        "studyType": "radiografia",
        "doctor": "Carla",
        "date": "Thu Oct 06 2022 08:45:51 GMT-0300 (hora estándar de Argentina)",
        "color": "dami"
    },
    {
        "id": "_wlrcjbim19f",
        "number": 268,
        "name": "FERNANDEZ ALEJANDRO",
        "tel": "2914255730",
        "os": "IOMA",
        "study": "DENTAL",
        "cash": "800",
        "card": 0,
        "studyType": "radiografia",
        "doctor": "Carla",
        "date": "Thu Oct 06 2022 08:44:36 GMT-0300 (hora estándar de Argentina)",
        "color": "dami"
    },
    {
        "id": "_9lzmyj328k",
        "number": 267,
        "name": "ZAMORA ANDREA",
        "tel": "2915040562",
        "os": "MEDIFE",
        "study": "PIE FYP",
        "cash": 0,
        "card": 0,
        "studyType": "radiografia",
        "doctor": "Carla",
        "date": "Thu Oct 06 2022 08:43:39 GMT-0300 (hora estándar de Argentina)",
        "color": "dami"
    },
    {
        "id": "_017ed8h4707g",
        "number": 266,
        "name": "RONCA MARIA",
        "tel": "2915742188",
        "os": "PATRONES",
        "study": "PIE FYP",
        "cash": "300",
        "card": 0,
        "studyType": "radiografia",
        "doctor": "Carla",
        "date": "Thu Oct 06 2022 08:41:11 GMT-0300 (hora estándar de Argentina)",
        "color": "dami"
    }
]